rtl/arm7tdmi_exception.sv
import arm7tdmi_pkg::*;

module arm7tdmi_exception (
    input  logic        clk,
    input  logic        rst_n,
    
    // Exception inputs
    input  logic        irq,
    input  logic        fiq,
    input  logic        swi,
    input  logic        undefined_instr,
    input  logic        prefetch_abort,
    input  logic        data_abort,
    
    // Current processor state
    input  processor_mode_t current_mode,
    input  logic [31:0]     current_cpsr,
    input  logic [31:0]     current_pc,
    
    // Exception control
    output logic            exception_taken,
    output processor_mode_t exception_mode,
    output logic [31:0]     exception_vector,
    output logic [31:0]     exception_cpsr,
    output logic [31:0]     exception_spsr,
    
    // Exception priority (highest priority exception)
    output logic [2:0]      exception_type
);

    // Exception types
    parameter EXCEPT_RESET        = 3'd0;
    parameter EXCEPT_UNDEFINED    = 3'd1;
    parameter EXCEPT_SWI          = 3'd2;
    parameter EXCEPT_PREFETCH_ABT = 3'd3;
    parameter EXCEPT_DATA_ABT     = 3'd4;
    parameter EXCEPT_IRQ          = 3'd5;
    parameter EXCEPT_FIQ          = 3'd6;
    
    // Exception vectors
    parameter VECTOR_RESET        = 32'h00000000;
    parameter VECTOR_UNDEFINED    = 32'h00000004;
    parameter VECTOR_SWI          = 32'h00000008;
    parameter VECTOR_PREFETCH_ABT = 32'h0000000C;
    parameter VECTOR_DATA_ABT     = 32'h00000010;
    parameter VECTOR_IRQ          = 32'h00000018;
    parameter VECTOR_FIQ          = 32'h0000001C;
    
    // IRQ and FIQ disable bits
    logic irq_disabled, fiq_disabled;
    assign irq_disabled = current_cpsr[CPSR_I_BIT];
    assign fiq_disabled = current_cpsr[CPSR_F_BIT];
    
    // Exception priority logic (ARM7TDMI priority order)
    always_comb begin
        exception_taken = 1'b0;
        exception_type = EXCEPT_RESET;
        exception_mode = MODE_SUPERVISOR;
        exception_vector = VECTOR_RESET;
        
        // Priority order: Reset > Data Abort > FIQ > IRQ > Prefetch Abort > Undefined > SWI
        if (data_abort) begin
            exception_taken = 1'b1;
            exception_type = EXCEPT_DATA_ABT;
            exception_mode = MODE_ABORT;
            exception_vector = VECTOR_DATA_ABT;
        end else if (fiq && !fiq_disabled) begin
            exception_taken = 1'b1;
            exception_type = EXCEPT_FIQ;
            exception_mode = MODE_FIQ;
            exception_vector = VECTOR_FIQ;
        end else if (irq && !irq_disabled) begin
            exception_taken = 1'b1;
            exception_type = EXCEPT_IRQ;
            exception_mode = MODE_IRQ;
            exception_vector = VECTOR_IRQ;
        end else if (prefetch_abort) begin
            exception_taken = 1'b1;
            exception_type = EXCEPT_PREFETCH_ABT;
            exception_mode = MODE_ABORT;
            exception_vector = VECTOR_PREFETCH_ABT;
        end else if (undefined_instr) begin
            exception_taken = 1'b1;
            exception_type = EXCEPT_UNDEFINED;
            exception_mode = MODE_UNDEFINED;
            exception_vector = VECTOR_UNDEFINED;
        end else if (swi) begin
            exception_taken = 1'b1;
            exception_type = EXCEPT_SWI;
            exception_mode = MODE_SUPERVISOR;
            exception_vector = VECTOR_SWI;
        end
    end
    
    // Generate new CPSR for exception mode
    always_comb begin
        exception_cpsr = current_cpsr;
        
        if (exception_taken) begin
            // Set new processor mode
            exception_cpsr[4:0] = exception_mode;
            
            // Disable interrupts as appropriate
            case (exception_type)
                EXCEPT_FIQ: begin
                    exception_cpsr[CPSR_F_BIT] = 1'b1;  // Disable FIQ
                    exception_cpsr[CPSR_I_BIT] = 1'b1;  // Disable IRQ
                end
                EXCEPT_IRQ: begin
                    exception_cpsr[CPSR_I_BIT] = 1'b1;  // Disable IRQ
                end
                default: begin
                    exception_cpsr[CPSR_I_BIT] = 1'b1;  // Disable IRQ for other exceptions
                end
            endcase
            
            // Clear Thumb bit (exceptions always execute in ARM mode)
            exception_cpsr[CPSR_T_BIT] = 1'b0;
        end
    end
    
    // SPSR gets the old CPSR value
    assign exception_spsr = current_cpsr;

endmodule

sim/abort_simple_test_tb.sv
// Simple ARM7TDMI Abort Detection Test
// Tests abort signal propagation through exception handler

`timescale 1ns/1ps

import arm7tdmi_pkg::*;

module abort_simple_test_tb;
    
    // Clock and reset
    logic clk = 0;
    logic rst_n = 1;
    
    always #5 clk = ~clk;  // 100MHz clock
    
    // Exception handler signals
    logic        irq = 0;
    logic        fiq = 0;
    logic        swi = 0;
    logic        undefined_instr = 0;
    logic        prefetch_abort = 0;
    logic        data_abort = 0;
    
    processor_mode_t current_mode;
    logic [31:0]     current_cpsr;
    logic [31:0]     current_pc;
    
    logic            exception_taken;
    processor_mode_t exception_mode;
    logic [31:0]     exception_vector;
    logic [31:0]     exception_cpsr;
    logic [31:0]     exception_spsr;
    logic [2:0]      exception_type;
    
    // Test variables
    int test_count = 0;
    int test_passed = 0;
    
    // DUT instantiation
    arm7tdmi_exception u_exception (
        .clk                (clk),
        .rst_n              (rst_n),
        .irq                (irq),
        .fiq                (fiq),
        .swi                (swi),
        .undefined_instr    (undefined_instr),
        .prefetch_abort     (prefetch_abort),
        .data_abort         (data_abort),
        .current_mode       (current_mode),
        .current_cpsr       (current_cpsr),
        .current_pc         (current_pc),
        .exception_taken    (exception_taken),
        .exception_mode     (exception_mode),
        .exception_vector   (exception_vector),
        .exception_cpsr     (exception_cpsr),
        .exception_spsr     (exception_spsr),
        .exception_type     (exception_type)
    );
    
    // Test tasks
    task test_data_abort_exception();
        test_count++;
        $display("\nTest %d: Data Abort Exception", test_count);
        
        // Set current state
        current_mode = MODE_USER;
        current_cpsr = 32'h0000001F; // User mode, interrupts enabled
        current_pc = 32'h00001000;
        
        // Trigger data abort
        data_abort = 1'b1;
        @(posedge clk);
        
        // Check exception response
        if (exception_taken && 
            exception_mode == MODE_ABORT &&
            exception_vector == 32'h00000010 &&
            exception_type == 3'd4) begin // EXCEPT_DATA_ABT
            test_passed++;
            $display("  ✅ PASS: Data abort exception correctly generated");
            $display("    Mode: 0x%02X, Vector: 0x%08X", exception_mode, exception_vector);
        end else begin
            $display("  ❌ FAIL: Data abort exception incorrect");
            $display("    Expected: Mode=ABORT, Vector=0x00000010");
            $display("    Got: Mode=0x%02X, Vector=0x%08X, Taken=%b", 
                     exception_mode, exception_vector, exception_taken);
        end
        
        data_abort = 1'b0;
        @(posedge clk);
    endtask
    
    task test_prefetch_abort_exception();
        test_count++;
        $display("\nTest %d: Prefetch Abort Exception", test_count);
        
        // Set current state
        current_mode = MODE_USER;
        current_cpsr = 32'h0000001F;
        current_pc = 32'h00002000;
        
        // Trigger prefetch abort
        prefetch_abort = 1'b1;
        @(posedge clk);
        
        // Check exception response
        if (exception_taken && 
            exception_mode == MODE_ABORT &&
            exception_vector == 32'h0000000C &&
            exception_type == 3'd3) begin // EXCEPT_PREFETCH_ABT
            test_passed++;
            $display("  ✅ PASS: Prefetch abort exception correctly generated");
            $display("    Mode: 0x%02X, Vector: 0x%08X", exception_mode, exception_vector);
        end else begin
            $display("  ❌ FAIL: Prefetch abort exception incorrect");
            $display("    Expected: Mode=ABORT, Vector=0x0000000C");
            $display("    Got: Mode=0x%02X, Vector=0x%08X", exception_mode, exception_vector);
        end
        
        prefetch_abort = 1'b0;
        @(posedge clk);
    endtask
    
    task test_abort_priority();
        test_count++;
        $display("\nTest %d: Abort Exception Priority", test_count);
        
        // Data abort has higher priority than FIQ/IRQ
        current_mode = MODE_USER;
        current_cpsr = 32'h0000001F; // Interrupts enabled
        current_pc = 32'h00003000;
        
        // Trigger multiple exceptions
        data_abort = 1'b1;
        irq = 1'b1;
        fiq = 1'b1;
        @(posedge clk);
        
        // Should take data abort (highest priority)
        if (exception_taken && 
            exception_type == 3'd4 && // EXCEPT_DATA_ABT
            exception_vector == 32'h00000010) begin
            test_passed++;
            $display("  ✅ PASS: Data abort has correct priority");
        end else begin
            $display("  ❌ FAIL: Exception priority incorrect");
            $display("    Expected: Data Abort (type=4)");
            $display("    Got: type=%d", exception_type);
        end
        
        data_abort = 1'b0;
        irq = 1'b0;
        fiq = 1'b0;
        @(posedge clk);
    endtask
    
    task test_abort_cpsr_update();
        test_count++;
        $display("\nTest %d: Abort CPSR Update", test_count);
        
        // Test CPSR updates for abort
        current_mode = MODE_USER;
        current_cpsr = 32'h6000001F; // User mode, FIQ/IRQ enabled, N and Z set
        current_pc = 32'h00004000;
        
        // Trigger data abort
        data_abort = 1'b1;
        @(posedge clk);
        
        // Check CPSR updates
        if (exception_cpsr[4:0] == MODE_ABORT && // Mode changed to abort
            exception_cpsr[7] == 1'b1 &&         // IRQ disabled
            exception_cpsr[5] == 1'b0) begin     // Thumb bit cleared
            test_passed++;
            $display("  ✅ PASS: CPSR correctly updated for abort");
            $display("    New CPSR: 0x%08X", exception_cpsr);
        end else begin
            $display("  ❌ FAIL: CPSR update incorrect");
            $display("    Expected: Mode=ABORT(0x17), I=1, T=0");
            $display("    Got CPSR: 0x%08X", exception_cpsr);
        end
        
        data_abort = 1'b0;
        @(posedge clk);
    endtask
    
    // Main test sequence
    initial begin
        $dumpfile("abort_simple_test_tb.vcd");
        $dumpvars(0, abort_simple_test_tb);
        
        $display("=== ARM7TDMI Abort Exception Test ===");
        
        // Reset
        rst_n = 0;
        @(posedge clk);
        rst_n = 1;
        repeat(2) @(posedge clk);
        
        // Run tests
        test_data_abort_exception();
        test_prefetch_abort_exception();
        test_abort_priority();
        test_abort_cpsr_update();
        
        // Summary
        repeat(5) @(posedge clk);
        $display("\n=== Test Summary ===");
        $display("Tests Run: %d", test_count);
        $display("Tests Passed: %d", test_passed);
        $display("Pass Rate: %.1f%%", (test_passed * 100.0) / test_count);
        
        if (test_passed == test_count) begin
            $display("\n✅ ALL ABORT EXCEPTION TESTS PASSED!");
        end else begin
            $display("\n❌ SOME ABORT EXCEPTION TESTS FAILED");
        end
        
        $finish;
    end
    
    // Timeout watchdog
    initial begin
        #1000; // 1us timeout
        $display("ERROR: Test timeout!");
        $finish;
    end
    
endmodule

sim/abort_simple_test_tb.vcd
$date
	Fri Jul 25 11:11:28 2025
$end
$version
	Icarus Verilog
$end
$timescale
	1ps
$end
$scope module abort_simple_test_tb $end
$var wire 32 ! exception_vector [31:0] $end
$var wire 3 " exception_type [2:0] $end
$var wire 1 # exception_taken $end
$var wire 32 $ exception_spsr [31:0] $end
$var wire 5 % exception_mode [4:0] $end
$var wire 32 & exception_cpsr [31:0] $end
$var reg 1 ' clk $end
$var reg 32 ( current_cpsr [31:0] $end
$var reg 5 ) current_mode [4:0] $end
$var reg 32 * current_pc [31:0] $end
$var reg 1 + data_abort $end
$var reg 1 , fiq $end
$var reg 1 - irq $end
$var reg 1 . prefetch_abort $end
$var reg 1 / rst_n $end
$var reg 1 0 swi $end
$var reg 1 1 undefined_instr $end
$var integer 32 2 test_count [31:0] $end
$var integer 32 3 test_passed [31:0] $end
$scope module u_exception $end
$var wire 1 ' clk $end
$var wire 32 4 current_cpsr [31:0] $end
$var wire 5 5 current_mode [4:0] $end
$var wire 32 6 current_pc [31:0] $end
$var wire 1 + data_abort $end
$var wire 32 7 exception_spsr [31:0] $end
$var wire 1 , fiq $end
$var wire 1 - irq $end
$var wire 1 . prefetch_abort $end
$var wire 1 / rst_n $end
$var wire 1 0 swi $end
$var wire 1 1 undefined_instr $end
$var wire 1 8 irq_disabled $end
$var wire 1 9 fiq_disabled $end
$var reg 32 : exception_cpsr [31:0] $end
$var reg 5 ; exception_mode [4:0] $end
$var reg 1 # exception_taken $end
$var reg 3 < exception_type [2:0] $end
$var reg 32 = exception_vector [31:0] $end
$upscope $end
$scope task test_abort_cpsr_update $end
$upscope $end
$scope task test_abort_priority $end
$upscope $end
$scope task test_data_abort_exception $end
$upscope $end
$scope task test_prefetch_abort_exception $end
$upscope $end
$upscope $end
$enddefinitions $end
#0
$dumpvars
b0 =
b0 <
b10011 ;
bx :
x9
x8
bx 7
bx 6
bx 5
bx 4
b0 3
b0 2
01
00
0/
0.
0-
0,
0+
bx *
bx )
bx (
0'
bx &
b10011 %
bx $
0#
b0 "
b0 !
$end
#5000
1/
1'
#10000
0'
#15000
1'
#20000
0'
#25000
b10000 !
b10000 =
b10111 %
b10111 ;
b100 "
b100 <
1#
b10010111 &
b10010111 :
08
09
1+
b1000000000000 *
b1000000000000 6
b11111 $
b11111 7
b11111 (
b11111 4
b10000 )
b10000 5
b1 2
1'
#30000
0'
#35000
b11111 &
b11111 :
b0 !
b0 =
b10011 %
b10011 ;
b0 "
b0 <
0#
0+
b1 3
1'
#40000
0'
#45000
b10010111 &
b10010111 :
b1100 !
b1100 =
b10111 %
b10111 ;
b11 "
b11 <
1#
1.
b10000000000000 *
b10000000000000 6
b10 2
1'
#50000
0'
#55000
b11111 &
b11111 :
b0 !
b0 =
b10011 %
b10011 ;
b0 "
b0 <
0#
0.
b10 3
1'
#60000
0'
#65000
b10010111 &
b10010111 :
b10000 !
b10000 =
b10111 %
b10111 ;
b100 "
b100 <
1#
1,
1-
1+
b11000000000000 *
b11000000000000 6
b11 2
1'
#70000
0'
#75000
b11111 &
b11111 :
b0 !
b0 =
b10011 %
b10011 ;
b0 "
b0 <
0#
0,
0-
0+
b11 3
1'
#80000
0'
#85000
b10000 !
b10000 =
b10111 %
b10111 ;
b100 "
b100 <
1#
b1100000000000000000000010010111 &
b1100000000000000000000010010111 :
1+
b100000000000000 *
b100000000000000 6
b1100000000000000000000000011111 $
b1100000000000000000000000011111 7
b1100000000000000000000000011111 (
b1100000000000000000000000011111 4
b100 2
1'
#90000
0'
#95000
b1100000000000000000000000011111 &
b1100000000000000000000000011111 :
b0 !
b0 =
b10011 %
b10011 ;
b0 "
b0 <
0#
0+
b100 3
1'
