rtl/arm7tdmi_decode.sv
import arm7tdmi_pkg::*;

module arm7tdmi_decode (
    input  logic        clk,
    input  logic        rst_n,
    
    // Input from fetch stage
    input  logic [31:0] instruction,
    input  logic [31:0] pc_in,
    input  logic        instr_valid,
    input  logic        thumb_mode,
    
    // Decoded instruction outputs
    output condition_t  condition,
    output instr_type_t instr_type,
    output alu_op_t     alu_op,
    output logic [3:0]  rd,      // Destination register
    output logic [3:0]  rn,      // First operand register
    output logic [3:0]  rm,      // Second operand register (if register)
    output logic [11:0] immediate, // Immediate value
    output logic        imm_en,   // Use immediate instead of register
    output logic        set_flags, // Update condition flags
    output shift_type_t shift_type,
    output logic [4:0]  shift_amount,
    
    // Branch instruction outputs
    output logic        is_branch,
    output logic [23:0] branch_offset,
    output logic        branch_link,
    
    // Memory instruction outputs
    output logic        is_memory,
    output logic        mem_load,   // 1 for load, 0 for store
    output logic        mem_byte,   // 1 for byte, 0 for word
    output logic        mem_pre,    // Pre-index
    output logic        mem_up,     // Add offset
    output logic        mem_writeback,
    
    // PSR transfer instruction outputs
    output logic        psr_to_reg,    // 1 for MRS, 0 for MSR
    output logic        psr_spsr,      // 1 for SPSR, 0 for CPSR
    output logic        psr_immediate, // 1 for immediate MSR
    
    // Coprocessor instruction outputs
    output cp_op_t      cp_op,         // Coprocessor operation type
    output logic [3:0]  cp_num,        // Coprocessor number (0-15)
    output logic [3:0]  cp_rd,         // Coprocessor destination register
    output logic [3:0]  cp_rn,         // Coprocessor operand register
    output logic [2:0]  cp_opcode1,    // Coprocessor opcode 1
    output logic [2:0]  cp_opcode2,    // Coprocessor opcode 2 (for CDP)
    output logic        cp_load,       // 1 for load, 0 for store (LDC/STC)
    
    // Output to execute stage
    output logic [31:0] pc_out,
    output logic        decode_valid,
    
    // Pipeline control
    input  logic        stall,
    input  logic        flush
);

    // Instruction fields (ARM format)
    logic [3:0]  cond_field;
    logic [1:0]  op_class;
    logic [5:0]  op_code;
    logic [3:0]  rd_field, rn_field, rm_field;
    logic [11:0] imm_field;
    logic        i_bit, s_bit;
    logic [1:0]  shift_type_field;
    logic [4:0]  shift_amt_field;
    
    // Branch instruction fields
    logic [23:0] branch_offset_field;
    logic        l_bit;
    
    // Memory instruction fields
    logic        p_bit, u_bit, b_bit, w_bit, l_bit_mem;
    
    // Decode registers
    logic [31:0] pc_reg;
    logic        valid_reg;
    
    // Extract instruction fields
    assign cond_field = instruction[31:28];
    assign op_class = instruction[27:26];
    assign i_bit = instruction[25];
    assign op_code = instruction[24:19];  // For data processing
    assign s_bit = instruction[20];
    assign rn_field = instruction[19:16];
    assign rd_field = instruction[15:12];
    assign rm_field = instruction[3:0];
    assign imm_field = instruction[11:0];
    assign shift_type_field = instruction[6:5];
    assign shift_amt_field = instruction[11:7];
    
    // Branch fields
    assign l_bit = instruction[24];
    assign branch_offset_field = instruction[23:0];
    
    // Memory fields
    assign p_bit = instruction[24];      // Pre/post index
    assign u_bit = instruction[23];      // Up/down
    assign b_bit = instruction[22];      // Byte/word
    assign w_bit = instruction[21];      // Write-back
    assign l_bit_mem = instruction[20];  // Load/store
    
    // Pipeline registers
    always_ff @(posedge clk or negedge rst_n) begin
        if (!rst_n) begin
            pc_reg <= 32'b0;
            valid_reg <= 1'b0;
        end else if (flush) begin
            pc_reg <= 32'b0;
            valid_reg <= 1'b0;
        end else if (!stall) begin
            pc_reg <= pc_in;
            valid_reg <= instr_valid;
        end
    end
    
    // Instruction type decode
    always_comb begin
        instr_type = INSTR_UNDEFINED;
        
        if (!thumb_mode) begin  // ARM mode
            casez (instruction[27:25])
                3'b000: begin
                    if (instruction[7:4] == 4'b1001) begin
                        if (instruction[24:21] == 4'b0000) begin
                            instr_type = INSTR_MUL;
                        end else begin
                            instr_type = INSTR_MUL_LONG;
                        end
                    end else if ((instruction[24:21] == 4'b1000 || instruction[24:21] == 4'b1010) && 
                                instruction[20] == 1'b0 && instruction[19:16] == 4'b1111 && instruction[11:0] == 12'b000000000000) begin
                        // MRS: Move PSR to register (check before SWP)
                        instr_type = INSTR_PSR_TRANSFER;
                    end else if ((instruction[24:21] == 4'b1001 || instruction[24:21] == 4'b1011) && 
                                instruction[11:4] == 8'b00000000) begin
                        // MSR: Move register to PSR
                        instr_type = INSTR_PSR_TRANSFER;
                    end else if (instruction[24:21] == 4'b1000 && instruction[7:4] == 4'b0000) begin
                        instr_type = INSTR_SINGLE_SWAP;
                    end else begin
                        instr_type = INSTR_DATA_PROC;
                    end
                end
                3'b001: begin
                    if (instruction[27:23] == 5'b00110 && instruction[21:20] == 2'b10) begin
                        // MSR: Move immediate to PSR
                        instr_type = INSTR_PSR_TRANSFER;
                    end else begin
                        instr_type = INSTR_DATA_PROC;
                    end
                end
                3'b010: instr_type = INSTR_SINGLE_DT;
                3'b011: instr_type = INSTR_SINGLE_DT;
                3'b100: instr_type = INSTR_BLOCK_DT;
                3'b101: instr_type = INSTR_BRANCH;
                3'b110: instr_type = INSTR_COPROCESSOR;
                3'b111: begin
                    if (instruction[24]) begin
                        instr_type = INSTR_SWI;
                    end else begin
                        instr_type = INSTR_COPROCESSOR;
                    end
                end
            endcase
        end else begin
            // TODO: Implement Thumb instruction decode
            instr_type = INSTR_UNDEFINED;
        end
    end
    
    // Condition decode
    assign condition = cond_field;
    
    // ALU operation decode (for data processing instructions)
    assign alu_op = instruction[24:21];
    
    // Register assignments
    assign rd = rd_field;
    assign rn = rn_field;
    assign rm = rm_field;
    assign immediate = imm_field;
    assign imm_en = i_bit && (instr_type == INSTR_DATA_PROC);
    assign set_flags = s_bit && (instr_type == INSTR_DATA_PROC);
    
    // Shift decode
    assign shift_type = shift_type_field;
    assign shift_amount = shift_amt_field;
    
    // Branch decode
    assign is_branch = (instr_type == INSTR_BRANCH);
    assign branch_offset = branch_offset_field;
    assign branch_link = l_bit && is_branch;
    
    // Memory decode
    assign is_memory = (instr_type == INSTR_SINGLE_DT) || (instr_type == INSTR_BLOCK_DT);
    assign mem_load = l_bit_mem;
    assign mem_byte = b_bit;
    assign mem_pre = p_bit;
    assign mem_up = u_bit;
    assign mem_writeback = w_bit;
    
    // PSR transfer decode
    assign psr_to_reg = (instr_type == INSTR_PSR_TRANSFER) && !instruction[21];  // MRS = L=0, MSR = L=1
    assign psr_spsr = (instr_type == INSTR_PSR_TRANSFER) && instruction[22];     // SPSR = R=1, CPSR = R=0  
    assign psr_immediate = (instr_type == INSTR_PSR_TRANSFER) && instruction[25]; // Immediate MSR
    
    // Coprocessor decode
    always_comb begin
        cp_op = CP_CDP;
        cp_num = 4'b0;
        cp_rd = 4'b0;
        cp_rn = 4'b0;
        cp_opcode1 = 3'b0;
        cp_opcode2 = 3'b0;
        cp_load = 1'b0;
        
        if (instr_type == INSTR_COPROCESSOR) begin
            cp_num = instruction[11:8];  // Coprocessor number
            
            if (instruction[27:25] == 3'b110) begin
                // LDC/STC - Coprocessor data transfer
                cp_rd = instruction[15:12];     // CRd
                cp_opcode1 = instruction[23:21]; // Opcode
                cp_load = instruction[20];       // L bit
                
                if (cp_load) begin
                    cp_op = CP_LDC;
                end else begin
                    cp_op = CP_STC;
                end
            end else if (instruction[27:25] == 3'b111) begin
                if (instruction[4]) begin
                    // MCR/MRC - Coprocessor register transfer
                    cp_rd = instruction[15:12];     // Rd (ARM register)
                    cp_rn = instruction[19:16];     // CRn (coprocessor register)
                    cp_opcode1 = instruction[23:21]; // Opcode 1
                    cp_opcode2 = instruction[7:5];   // Opcode 2
                    
                    if (instruction[20]) begin
                        cp_op = CP_MRC;  // Move to ARM from coprocessor
                    end else begin
                        cp_op = CP_MCR;  // Move to coprocessor from ARM
                    end
                end else begin
                    // CDP - Coprocessor data processing
                    cp_op = CP_CDP;
                    cp_rd = instruction[15:12];     // CRd
                    cp_rn = instruction[19:16];     // CRn
                    cp_opcode1 = instruction[23:21]; // Opcode 1
                    cp_opcode2 = instruction[7:5];   // Opcode 2
                end
            end
        end
    end
    
    // Outputs
    assign pc_out = pc_reg;
    assign decode_valid = valid_reg;
    
endmodule

sim/coprocessor_decode_tb.sv
// Coprocessor Decode Test
`timescale 1ns/1ps

import arm7tdmi_pkg::*;

module coprocessor_decode_tb;
    
    // Clock and reset
    logic clk = 0;
    logic rst_n = 1;
    
    always #5 clk = ~clk;  // 100MHz clock
    
    // Decode stage signals
    logic [31:0] instruction;
    logic [31:0] pc_in = 32'h00000000;
    logic        instr_valid = 1'b1;
    logic        thumb_mode = 1'b0;
    logic        stall = 1'b0;
    logic        flush = 1'b0;
    
    // Decoded outputs
    condition_t  condition;
    instr_type_t instr_type;
    alu_op_t     alu_op;
    logic [3:0]  rd, rn, rm;
    logic [11:0] immediate;
    logic        imm_en, set_flags;
    shift_type_t shift_type;
    logic [4:0]  shift_amount;
    logic        is_branch, branch_link;
    logic [23:0] branch_offset;
    logic        is_memory, mem_load, mem_byte;
    logic        mem_pre, mem_up, mem_writeback;
    logic        psr_to_reg, psr_spsr, psr_immediate;
    cp_op_t      cp_op;
    logic [3:0]  cp_num, cp_rd, cp_rn;
    logic [2:0]  cp_opcode1, cp_opcode2;
    logic        cp_load;
    logic [31:0] pc_out;
    logic        decode_valid;
    
    // DUT instantiation
    arm7tdmi_decode u_decode (
        .clk            (clk),
        .rst_n          (rst_n),
        .instruction    (instruction),
        .pc_in          (pc_in),
        .instr_valid    (instr_valid),
        .thumb_mode     (thumb_mode),
        .condition      (condition),
        .instr_type     (instr_type),
        .alu_op         (alu_op),
        .rd             (rd),
        .rn             (rn),
        .rm             (rm),
        .immediate      (immediate),
        .imm_en         (imm_en),
        .set_flags      (set_flags),
        .shift_type     (shift_type),
        .shift_amount   (shift_amount),
        .is_branch      (is_branch),
        .branch_offset  (branch_offset),
        .branch_link    (branch_link),
        .is_memory      (is_memory),
        .mem_load       (mem_load),
        .mem_byte       (mem_byte),
        .mem_pre        (mem_pre),
        .mem_up         (mem_up),
        .mem_writeback  (mem_writeback),
        .psr_to_reg     (psr_to_reg),
        .psr_spsr       (psr_spsr),
        .psr_immediate  (psr_immediate),
        .cp_op          (cp_op),
        .cp_num         (cp_num),
        .cp_rd          (cp_rd),
        .cp_rn          (cp_rn),
        .cp_opcode1     (cp_opcode1),
        .cp_opcode2     (cp_opcode2),
        .cp_load        (cp_load),
        .pc_out         (pc_out),
        .decode_valid   (decode_valid),
        .stall          (stall),
        .flush          (flush)
    );
    
    initial begin
        $dumpfile("coprocessor_decode_tb.vcd");
        $dumpvars(0, coprocessor_decode_tb);
        
        rst_n = 0;
        repeat(2) @(posedge clk);
        rst_n = 1;
        @(posedge clk);
        
        $display("=== Coprocessor Decode Test ===");
        
        // Test 1: MRC p15, 0, R0, c0, c0, 0 (Read CP15 ID register)
        instruction = 32'hEE100F10;
        @(posedge clk);
        @(posedge clk);  // Wait for decode
        $display("Test 1 - MRC p15, 0, R0, c0, c0, 0 (0x%08h):", instruction);
        $display("  instr_type = %d", instr_type);
        $display("  cp_op = %d, cp_num = %d", cp_op, cp_num);
        $display("  cp_rd = %d, cp_rn = %d", cp_rd, cp_rn);
        $display("  cp_opcode1 = %d, cp_opcode2 = %d", cp_opcode1, cp_opcode2);
        if (instr_type == INSTR_COPROCESSOR && cp_op == CP_MRC && cp_num == 15 && 
            cp_rd == 0 && cp_rn == 0 && cp_opcode1 == 0 && cp_opcode2 == 0) begin
            $display("  PASS");
        end else begin
            $display("  FAIL");
        end
        
        // Test 2: MCR p15, 0, R2, c1, c0, 0 (Write CP15 Control register)
        instruction = 32'hEE012F10;
        @(posedge clk);
        @(posedge clk);  // Wait for decode
        $display("Test 2 - MCR p15, 0, R2, c1, c0, 0 (0x%08h):", instruction);
        $display("  instr_type = %d", instr_type);
        $display("  cp_op = %d, cp_num = %d", cp_op, cp_num);
        $display("  cp_rd = %d, cp_rn = %d", cp_rd, cp_rn);
        $display("  cp_opcode1 = %d, cp_opcode2 = %d", cp_opcode1, cp_opcode2);
        if (instr_type == INSTR_COPROCESSOR && cp_op == CP_MCR && cp_num == 15 && 
            cp_rd == 2 && cp_rn == 1 && cp_opcode1 == 0 && cp_opcode2 == 0) begin
            $display("  PASS");
        end else begin
            $display("  FAIL");
        end
        
        // Test 3: LDC p10, c5, [R1, #16] (Load coprocessor)
        instruction = 32'hED915A04;
        @(posedge clk);
        @(posedge clk);  // Wait for decode
        $display("Test 3 - LDC p10, c5, [R1, #16] (0x%08h):", instruction);
        $display("  instr_type = %d", instr_type);
        $display("  cp_op = %d, cp_num = %d", cp_op, cp_num);
        $display("  cp_rd = %d, cp_load = %b", cp_rd, cp_load);
        $display("  cp_opcode1 = %d", cp_opcode1);
        if (instr_type == INSTR_COPROCESSOR && cp_op == CP_LDC && cp_num == 10 && 
            cp_rd == 5 && cp_load == 1) begin
            $display("  PASS");
        end else begin
            $display("  FAIL");
        end
        
        // Test 4: STC p10, c4, [R2, #-8] (Store coprocessor)
        instruction = 32'hED024AFE;
        @(posedge clk);
        @(posedge clk);  // Wait for decode
        $display("Test 4 - STC p10, c4, [R2, #-8] (0x%08h):", instruction);
        $display("  instr_type = %d", instr_type);
        $display("  cp_op = %d, cp_num = %d", cp_op, cp_num);
        $display("  cp_rd = %d, cp_load = %b", cp_rd, cp_load);
        $display("  cp_opcode1 = %d", cp_opcode1);
        if (instr_type == INSTR_COPROCESSOR && cp_op == CP_STC && cp_num == 10 && 
            cp_rd == 4 && cp_load == 0) begin
            $display("  PASS");
        end else begin
            $display("  FAIL");
        end
        
        // Test 5: CDP p10, 2, c4, c5, c6, 3 (Coprocessor data processing)  
        instruction = 32'hEE464A66;
        @(posedge clk);
        @(posedge clk);  // Wait for decode
        $display("Test 5 - CDP p10, 2, c4, c5, c6, 3 (0x%08h):", instruction);
        $display("  instr_type = %d", instr_type);
        $display("  cp_op = %d, cp_num = %d", cp_op, cp_num);
        $display("  cp_rd = %d, cp_rn = %d", cp_rd, cp_rn);
        $display("  cp_opcode1 = %d, cp_opcode2 = %d", cp_opcode1, cp_opcode2);
        if (instr_type == INSTR_COPROCESSOR && cp_op == CP_CDP && cp_num == 10 && 
            cp_rd == 4 && cp_rn == 6 && cp_opcode1 == 2 && cp_opcode2 == 3) begin
            $display("  PASS");
        end else begin
            $display("  FAIL");
        end
        
        // Test 6: ADD R0, R0, R1 (Verify non-coprocessor instruction still works)
        instruction = 32'hE0800001;
        @(posedge clk);
        @(posedge clk);  // Wait for decode
        $display("Test 6 - ADD R0, R0, R1 (0x%08h):", instruction);
        $display("  instr_type = %d", instr_type);
        if (instr_type == INSTR_DATA_PROC) begin
            $display("  PASS - Correctly identified as data processing");
        end else begin
            $display("  FAIL - Should be data processing");
        end
        
        $display("=== Coprocessor Decode Test Complete ===");
        $finish;
    end
    
endmodule

sim/coprocessor_decode_tb.vcd
$date
	Thu Jul 24 14:19:57 2025
$end
$version
	Icarus Verilog
$end
$timescale
	1ps
$end
$scope module coprocessor_decode_tb $end
$var wire 2 ! shift_type [1:0] $end
$var wire 5 " shift_amount [4:0] $end
$var wire 1 # set_flags $end
$var wire 4 $ rn [3:0] $end
$var wire 4 % rm [3:0] $end
$var wire 4 & rd [3:0] $end
$var wire 1 ' psr_to_reg $end
$var wire 1 ( psr_spsr $end
$var wire 1 ) psr_immediate $end
$var wire 32 * pc_out [31:0] $end
$var wire 1 + mem_writeback $end
$var wire 1 , mem_up $end
$var wire 1 - mem_pre $end
$var wire 1 . mem_load $end
$var wire 1 / mem_byte $end
$var wire 1 0 is_memory $end
$var wire 1 1 is_branch $end
$var wire 4 2 instr_type [3:0] $end
$var wire 12 3 immediate [11:0] $end
$var wire 1 4 imm_en $end
$var wire 1 5 decode_valid $end
$var wire 4 6 cp_rn [3:0] $end
$var wire 4 7 cp_rd [3:0] $end
$var wire 3 8 cp_opcode2 [2:0] $end
$var wire 3 9 cp_opcode1 [2:0] $end
$var wire 3 : cp_op [2:0] $end
$var wire 4 ; cp_num [3:0] $end
$var wire 1 < cp_load $end
$var wire 4 = condition [3:0] $end
$var wire 24 > branch_offset [23:0] $end
$var wire 1 ? branch_link $end
$var wire 4 @ alu_op [3:0] $end
$var reg 1 A clk $end
$var reg 1 B flush $end
$var reg 1 C instr_valid $end
$var reg 32 D instruction [31:0] $end
$var reg 32 E pc_in [31:0] $end
$var reg 1 F rst_n $end
$var reg 1 G stall $end
$var reg 1 H thumb_mode $end
$scope module u_decode $end
$var wire 1 ? branch_link $end
$var wire 24 I branch_offset [23:0] $end
$var wire 1 A clk $end
$var wire 4 J condition [3:0] $end
$var wire 1 5 decode_valid $end
$var wire 1 B flush $end
$var wire 1 4 imm_en $end
$var wire 12 K immediate [11:0] $end
$var wire 1 C instr_valid $end
$var wire 32 L instruction [31:0] $end
$var wire 1 0 is_memory $end
$var wire 1 / mem_byte $end
$var wire 1 . mem_load $end
$var wire 1 - mem_pre $end
$var wire 1 , mem_up $end
$var wire 1 + mem_writeback $end
$var wire 32 M pc_in [31:0] $end
$var wire 32 N pc_out [31:0] $end
$var wire 1 ) psr_immediate $end
$var wire 1 ( psr_spsr $end
$var wire 1 ' psr_to_reg $end
$var wire 4 O rd [3:0] $end
$var wire 4 P rm [3:0] $end
$var wire 4 Q rn [3:0] $end
$var wire 1 F rst_n $end
$var wire 1 # set_flags $end
$var wire 5 R shift_amount [4:0] $end
$var wire 2 S shift_type [1:0] $end
$var wire 1 G stall $end
$var wire 1 H thumb_mode $end
$var wire 1 T w_bit $end
$var wire 1 U u_bit $end
$var wire 2 V shift_type_field [1:0] $end
$var wire 5 W shift_amt_field [4:0] $end
$var wire 1 X s_bit $end
$var wire 4 Y rn_field [3:0] $end
$var wire 4 Z rm_field [3:0] $end
$var wire 4 [ rd_field [3:0] $end
$var wire 1 \ p_bit $end
$var wire 6 ] op_code [5:0] $end
$var wire 2 ^ op_class [1:0] $end
$var wire 1 _ l_bit_mem $end
$var wire 1 ` l_bit $end
$var wire 1 1 is_branch $end
$var wire 12 a imm_field [11:0] $end
$var wire 1 b i_bit $end
$var wire 4 c cond_field [3:0] $end
$var wire 24 d branch_offset_field [23:0] $end
$var wire 1 e b_bit $end
$var wire 4 f alu_op [3:0] $end
$var reg 1 < cp_load $end
$var reg 4 g cp_num [3:0] $end
$var reg 3 h cp_op [2:0] $end
$var reg 3 i cp_opcode1 [2:0] $end
$var reg 3 j cp_opcode2 [2:0] $end
$var reg 4 k cp_rd [3:0] $end
$var reg 4 l cp_rn [3:0] $end
$var reg 4 m instr_type [3:0] $end
$var reg 32 n pc_reg [31:0] $end
$var reg 1 o valid_reg $end
$upscope $end
$upscope $end
$enddefinitions $end
#0
$dumpvars
0o
b0 n
b111 m
b0 l
b0 k
b0 j
b0 i
b0 h
b0 g
bx f
xe
bx d
bx c
xb
bx a
x`
x_
bx ^
bx ]
x\
bx [
bx Z
bx Y
xX
bx W
bx V
xU
xT
bx S
bx R
bx Q
bx P
bx O
b0 N
b0 M
bx L
bx K
bx J
bx I
0H
0G
0F
b0 E
bx D
1C
0B
0A
bx @
0?
bx >
bx =
0<
b0 ;
b0 :
b0 9
b0 8
b0 7
b0 6
05
04
bx 3
b111 2
01
00
x/
x.
x-
x,
x+
b0 *
0)
0(
0'
bx &
bx %
bx $
0#
bx "
bx !
$end
#5000
1A
#10000
0A
#15000
15
1o
1F
1A
#20000
0A
#25000
b100 :
b100 h
b1111 ;
b1111 g
b1010 2
b1010 m
b1110 =
b1110 J
b1110 c
b11 ^
1b
b10 ]
1X
b0 $
b0 Q
b0 Y
b0 &
b0 O
b0 [
b0 %
b0 P
b0 Z
b111100010000 3
b111100010000 K
b111100010000 a
b0 !
b0 S
b0 V
b11110 "
b11110 R
b11110 W
0`
b100000000111100010000 >
b100000000111100010000 I
b100000000111100010000 d
0-
0\
0,
0U
0/
0e
0+
0T
1.
1_
b0 @
b0 f
b11101110000100000000111100010000 D
b11101110000100000000111100010000 L
1A
#30000
0A
#35000
1A
#40000
0A
#45000
b1 6
b1 l
b10 7
b10 k
b1111 ;
b1111 g
b11 :
b11 h
b1010 2
b1010 m
b0 ]
0X
b1 $
b1 Q
b1 Y
b10 &
b10 O
b10 [
b10010111100010000 >
b10010111100010000 I
b10010111100010000 d
0.
0_
b11101110000000010010111100010000 D
b11101110000000010010111100010000 L
1A
#50000
0A
#55000
1A
#60000
0A
#65000
1<
b100 9
b100 i
b0 6
b0 l
b101 7
b101 k
b1010 ;
b1010 g
b1 :
b1 h
b1010 2
b1010 m
0b
b110010 ]
1X
b101 &
b101 O
b101 [
b100 %
b100 P
b100 Z
b101000000100 3
b101000000100 K
b101000000100 a
b10100 "
b10100 R
b10100 W
1`
b100100010101101000000100 >
b100100010101101000000100 I
b100100010101101000000100 d
1-
1\
1,
1U
1.
1_
b1100 @
b1100 f
b11101101100100010101101000000100 D
b11101101100100010101101000000100 L
1A
#70000
0A
#75000
1A
#80000
0A
#85000
0<
b0 9
b0 i
b100 7
b100 k
b1010 ;
b1010 g
b10 :
b10 h
b1010 2
b1010 m
b100000 ]
0X
b10 $
b10 Q
b10 Y
b100 &
b100 O
b100 [
b1110 %
b1110 P
b1110 Z
b101011111110 3
b101011111110 K
b101011111110 a
b11 !
b11 S
b11 V
b10101 "
b10101 R
b10101 W
b100100101011111110 >
b100100101011111110 I
b100100101011111110 d
0,
0U
0.
0_
b1000 @
b1000 f
b11101101000000100100101011111110 D
b11101101000000100100101011111110 L
1A
#90000
0A
#95000
1A
#100000
0A
#105000
b11 8
b11 j
b10 9
b10 i
b110 6
b110 l
b100 7
b100 k
b1010 ;
b1010 g
b0 :
b0 h
b1010 2
b1010 m
1b
b1000 ]
b110 $
b110 Q
b110 Y
b110 %
b110 P
b110 Z
b101001100110 3
b101001100110 K
b101001100110 a
b10100 "
b10100 R
b10100 W
0`
b10001100100101001100110 >
b10001100100101001100110 I
b10001100100101001100110 d
0-
0\
1/
1e
b10 @
b10 f
b11101110010001100100101001100110 D
b11101110010001100100101001100110 L
1A
#110000
0A
#115000
1A
#120000
0A
#125000
b0 8
b0 j
b0 9
b0 i
b0 6
b0 l
b0 7
b0 k
b0 ;
b0 g
b0 2
b0 m
b0 ^
0b
b10000 ]
b0 $
b0 Q
b0 Y
b0 &
b0 O
b0 [
b1 %
b1 P
b1 Z
b1 3
b1 K
b1 a
b0 !
b0 S
b0 V
b0 "
b0 R
b0 W
b100000000000000000000001 >
b100000000000000000000001 I
b100000000000000000000001 d
1,
1U
0/
0e
b100 @
b100 f
b11100000100000000000000000000001 D
b11100000100000000000000000000001 L
1A
