rtl/arm7tdmi_coprocessor.sv
// ARM7TDMI Coprocessor Interface
// Implements CP15 system control coprocessor and generic coprocessor interface

`timescale 1ns/1ps

module arm7tdmi_coprocessor
    import arm7tdmi_pkg::*;
(
    input  logic        clk,
    input  logic        rst_n,
    
    // Coprocessor interface from decode stage
    input  logic        cp_en,          // Coprocessor enable
    input  cp_op_t      cp_op,          // Coprocessor operation
    input  logic [3:0]  cp_num,         // Coprocessor number (0-15)
    input  logic [3:0]  cp_crn,         // Coprocessor register N
    input  logic [3:0]  cp_crm,         // Coprocessor register M  
    input  logic [2:0]  cp_op1,         // Opcode 1
    input  logic [2:0]  cp_op2,         // Opcode 2
    input  logic [31:0] cp_data_in,     // Data from ARM register
    
    // Coprocessor response
    output logic        cp_busy,        // Coprocessor busy
    output logic        cp_absent,      // Coprocessor absent
    output logic [31:0] cp_data_out,    // Data to ARM register
    
    // System control interface
    output logic        mmu_enable,     // Enable MMU
    output logic        dcache_enable,  // Enable data cache
    output logic        icache_enable,  // Enable instruction cache
    output logic        write_buffer_en,// Enable write buffer
    output logic [31:0] ttb_base,       // Translation table base
    output logic [1:0]  ttb_ctrl,       // Translation table control
    output logic [31:0] domain_access,  // Domain access control
    output logic        high_vectors,   // High exception vectors
    output logic        rom_protection, // ROM protection
    output logic        system_protect, // System protection
    
    // Cache control
    output logic        dcache_clean,   // Clean data cache
    output logic        dcache_flush,   // Flush data cache
    output logic        icache_flush,   // Flush instruction cache
    output logic        tlb_flush,      // Flush TLB
    
    // System information
    output logic [31:0] cpu_id,         // CPU ID register
    output logic [31:0] cache_type,     // Cache type register
    
    // Debug interface
    input  logic        debug_mode,     // In debug mode
    output logic [31:0] cp15_reg_out    // CP15 register value for debug
);

    //===========================================
    // CP15 System Control Coprocessor Registers
    //===========================================
    
    // CP15 Register Map (CRn, op1, CRm, op2)
    // c0 - ID registers
    // c1 - Control register
    // c2 - Translation table base
    // c3 - Domain access control
    // c5 - Fault status
    // c6 - Fault address
    // c7 - Cache operations
    // c8 - TLB operations
    // c9 - Cache lockdown
    // c13 - Process ID
    // c15 - Test and debug
    
    // Control Register (c1) - individual bits for better compatibility
    logic ctrl_m;       // MMU enable (bit 0)
    logic ctrl_a;       // Alignment check enable (bit 1)
    logic ctrl_c;       // Data cache enable (bit 2)
    logic ctrl_s;       // System protection (bit 8)
    logic ctrl_r;       // ROM protection (bit 9)
    logic ctrl_z;       // Branch prediction enable (bit 11)
    logic ctrl_i;       // Instruction cache enable (bit 12)
    logic ctrl_v;       // High vectors (bit 13)
    
    // Other CP15 registers
    logic [31:0] translation_table_base;
    logic [31:0] domain_access_ctrl;
    logic [31:0] fault_status;
    logic [31:0] fault_address;
    logic [31:0] process_id;
    
    // Cache operation trigger signals  
    logic icache_flush_trigger;
    logic dcache_flush_trigger;
    logic dcache_clean_trigger;
    logic tlb_flush_trigger;
    
    // Delayed cache operation signals (persist for one cycle after MCR)
    logic icache_flush_delayed;
    logic dcache_flush_delayed;
    logic dcache_clean_delayed;
    logic tlb_flush_delayed;
    
    // Fixed ID registers
    assign cpu_id = 32'h41007000;      // ARM7TDMI ID
    assign cache_type = 32'h0f002002;  // 8KB I-cache, 8KB D-cache
    
    //===========================================
    // Coprocessor Absent Logic
    //===========================================
    
    // Only CP15 is present in ARM7TDMI
    assign cp_absent = cp_en && (cp_num != 4'd15);
    
    // CP15 is never busy (single-cycle operations)
    assign cp_busy = 1'b0;
    
    //===========================================
    // CP15 Register Access
    //===========================================
    
    always_ff @(posedge clk or negedge rst_n) begin
        if (!rst_n) begin
            ctrl_m <= 1'b0;
            ctrl_a <= 1'b0;
            ctrl_c <= 1'b0;
            ctrl_s <= 1'b0;
            ctrl_r <= 1'b0;
            ctrl_z <= 1'b0;
            ctrl_i <= 1'b0;
            ctrl_v <= 1'b0;
            translation_table_base <= 32'h0;
            domain_access_ctrl <= 32'h0;
            fault_status <= 32'h0;
            fault_address <= 32'h0;
            process_id <= 32'h0;
            
            // Cache operation triggers
            icache_flush_trigger <= 1'b0;
            dcache_flush_trigger <= 1'b0;
            dcache_clean_trigger <= 1'b0;
            tlb_flush_trigger <= 1'b0;
            
            // Delayed cache signals
            icache_flush_delayed <= 1'b0;
            dcache_flush_delayed <= 1'b0;
            dcache_clean_delayed <= 1'b0;
            tlb_flush_delayed <= 1'b0;
        end else begin
            // Clear trigger signals by default
            icache_flush_trigger <= 1'b0;
            dcache_flush_trigger <= 1'b0;
            dcache_clean_trigger <= 1'b0;
            tlb_flush_trigger <= 1'b0;
            
            if (cp_en && !cp_absent && !debug_mode) begin
                case (cp_op)
                    CP_CDP: begin
                        // Coprocessor data operation - not used in CP15
                    end
                    
                    CP_MRC: begin
                        // Move from coprocessor to ARM register
                        // Nothing to do here - handled in read logic below
                    end
                    
                    CP_MCR: begin
                        // Move from ARM register to coprocessor
                        case (cp_crn)
                            4'd1: begin // Control register
                                if (cp_crm == 4'd0 && cp_op1 == 3'd0 && cp_op2 == 3'd0) begin
                                    ctrl_m <= cp_data_in[0];    // MMU enable
                                    ctrl_a <= cp_data_in[1];    // Alignment check
                                    ctrl_c <= cp_data_in[2];    // Data cache enable
                                    ctrl_s <= cp_data_in[8];    // System protection
                                    ctrl_r <= cp_data_in[9];    // ROM protection
                                    ctrl_z <= cp_data_in[11];   // Branch prediction
                                    ctrl_i <= cp_data_in[12];   // Instruction cache enable
                                    ctrl_v <= cp_data_in[13];   // High vectors
                                end
                            end
                            
                            4'd2: begin // Translation table base
                                if (cp_crm == 4'd0 && cp_op1 == 3'd0 && cp_op2 == 3'd0) begin
                                    translation_table_base <= cp_data_in;
                                end
                            end
                            
                            4'd3: begin // Domain access control
                                if (cp_crm == 4'd0 && cp_op1 == 3'd0 && cp_op2 == 3'd0) begin
                                    domain_access_ctrl <= cp_data_in;
                                end
                            end
                            
                            4'd5: begin // Fault status
                                if (cp_crm == 4'd0 && cp_op1 == 3'd0 && cp_op2 == 3'd0) begin
                                    fault_status <= cp_data_in;
                                end
                            end
                            
                            4'd6: begin // Fault address
                                if (cp_crm == 4'd0 && cp_op1 == 3'd0 && cp_op2 == 3'd0) begin
                                    fault_address <= cp_data_in;
                                end
                            end
                            
                            4'd7: begin // Cache operations
                                case ({cp_crm, cp_op2})
                                    7'b0101000: icache_flush_trigger <= 1'b1;  // Flush I-cache
                                    7'b0110000: dcache_flush_trigger <= 1'b1;  // Flush D-cache
                                    7'b1010001: dcache_clean_trigger <= 1'b1;  // Clean D-cache
                                    7'b1110001: begin                          // Clean and flush D-cache
                                        dcache_clean_trigger <= 1'b1;
                                        dcache_flush_trigger <= 1'b1;
                                    end
                                endcase
                            end
                            
                            4'd8: begin // TLB operations
                                case ({cp_crm, cp_op2})
                                    7'b0111000: tlb_flush_trigger <= 1'b1;      // Flush entire TLB
                                endcase
                            end
                            
                            4'd13: begin // Process ID
                                if (cp_crm == 4'd0 && cp_op1 == 3'd0 && cp_op2 == 3'd0) begin
                                    process_id <= cp_data_in;
                                end
                            end
                            
                        endcase
                    end
                    
                    default: begin
                        // LDC, STC not supported by CP15
                    end
                endcase
            end
            
            // Update delayed cache signals  
            icache_flush_delayed <= icache_flush_trigger;
            dcache_flush_delayed <= dcache_flush_trigger;
            dcache_clean_delayed <= dcache_clean_trigger;
            tlb_flush_delayed <= tlb_flush_trigger;
        end
    end
    
    //===========================================
    // CP15 Register Read
    //===========================================
    
    always_comb begin
        cp_data_out = 32'h0;
        
        if (cp_en && !cp_absent && cp_op == CP_MRC) begin
            case (cp_crn)
                4'd0: begin // ID registers
                    case ({cp_op1, cp_crm, cp_op2})
                        9'b000000000: cp_data_out = cpu_id;      // Main ID
                        9'b000000001: cp_data_out = cache_type;  // Cache type
                        default: cp_data_out = 32'h0;
                    endcase
                end
                
                4'd1: begin // Control register
                    if (cp_crm == 4'd0 && cp_op1 == 3'd0 && cp_op2 == 3'd0) begin
                        cp_data_out = {18'h0, ctrl_v, ctrl_i, ctrl_z, 1'b0, 
                                      ctrl_r, ctrl_s, 1'b0, 4'h0, ctrl_c, 
                                      ctrl_a, ctrl_m};
                    end
                end
                
                4'd2: begin // Translation table base
                    if (cp_crm == 4'd0 && cp_op1 == 3'd0 && cp_op2 == 3'd0) begin
                        cp_data_out = translation_table_base;
                    end
                end
                
                4'd3: begin // Domain access control
                    if (cp_crm == 4'd0 && cp_op1 == 3'd0 && cp_op2 == 3'd0) begin
                        cp_data_out = domain_access_ctrl;
                    end
                end
                
                4'd5: begin // Fault status
                    if (cp_crm == 4'd0 && cp_op1 == 3'd0 && cp_op2 == 3'd0) begin
                        cp_data_out = fault_status;
                    end
                end
                
                4'd6: begin // Fault address
                    if (cp_crm == 4'd0 && cp_op1 == 3'd0 && cp_op2 == 3'd0) begin
                        cp_data_out = fault_address;
                    end
                end
                
                4'd13: begin // Process ID
                    if (cp_crm == 4'd0 && cp_op1 == 3'd0 && cp_op2 == 3'd0) begin
                        cp_data_out = process_id;
                    end
                end
                
                default: cp_data_out = 32'h0;
            endcase
        end
    end
    
    //===========================================
    // System Control Outputs
    //===========================================
    
    assign mmu_enable = ctrl_m;
    assign dcache_enable = ctrl_c;
    assign icache_enable = ctrl_i;
    assign write_buffer_en = ctrl_c;  // Same as D-cache
    assign high_vectors = ctrl_v;
    assign rom_protection = ctrl_r;
    assign system_protect = ctrl_s;
    
    assign ttb_base = translation_table_base;
    assign ttb_ctrl = translation_table_base[1:0];  // N value
    assign domain_access = domain_access_ctrl;
    
    //===========================================
    // Cache Control Signal Generation
    //===========================================
    
    assign dcache_clean = dcache_clean_delayed;
    assign dcache_flush = dcache_flush_delayed;
    assign icache_flush = icache_flush_delayed;
    assign tlb_flush = tlb_flush_delayed;
    
    // Debug output
    assign cp15_reg_out = {18'h0, ctrl_v, ctrl_i, ctrl_z, 1'b0, 
                          ctrl_r, ctrl_s, 1'b0, 4'h0, ctrl_c, 
                          ctrl_a, ctrl_m};

endmodule

sim/coprocessor_test_tb.sv
// Testbench for ARM7TDMI Coprocessor Interface (CP15)
`timescale 1ns/1ps

module coprocessor_test_tb;

    // Import package
    import arm7tdmi_pkg::*;
    
    // Clock and reset
    logic clk;
    logic rst_n;
    
    // Coprocessor interface
    logic        cp_en;
    cp_op_t      cp_op;
    logic [3:0]  cp_num;
    logic [3:0]  cp_crn;
    logic [3:0]  cp_crm;
    logic [2:0]  cp_op1;
    logic [2:0]  cp_op2;
    logic [31:0] cp_data_in;
    
    // Coprocessor response
    logic        cp_busy;
    logic        cp_absent;
    logic [31:0] cp_data_out;
    
    // System control outputs
    logic        mmu_enable;
    logic        dcache_enable;
    logic        icache_enable;
    logic        write_buffer_en;
    logic [31:0] ttb_base;
    logic [1:0]  ttb_ctrl;
    logic [31:0] domain_access;
    logic        high_vectors;
    logic        rom_protection;
    logic        system_protect;
    
    // Cache control
    logic        dcache_clean;
    logic        dcache_flush;
    logic        icache_flush;
    logic        tlb_flush;
    
    // System information
    logic [31:0] cpu_id;
    logic [31:0] cache_type;
    
    // Debug
    logic        debug_mode = 0;
    logic [31:0] cp15_reg_out;
    
    // Test variables
    int tests_run = 0;
    int tests_passed = 0;
    
    // DUT instantiation
    arm7tdmi_coprocessor u_coprocessor (
        .clk                (clk),
        .rst_n              (rst_n),
        .cp_en              (cp_en),
        .cp_op              (cp_op),
        .cp_num             (cp_num),
        .cp_crn             (cp_crn),
        .cp_crm             (cp_crm),
        .cp_op1             (cp_op1),
        .cp_op2             (cp_op2),
        .cp_data_in         (cp_data_in),
        .cp_busy            (cp_busy),
        .cp_absent          (cp_absent),
        .cp_data_out        (cp_data_out),
        .mmu_enable         (mmu_enable),
        .dcache_enable      (dcache_enable),
        .icache_enable      (icache_enable),
        .write_buffer_en    (write_buffer_en),
        .ttb_base           (ttb_base),
        .ttb_ctrl           (ttb_ctrl),
        .domain_access      (domain_access),
        .high_vectors       (high_vectors),
        .rom_protection     (rom_protection),
        .system_protect     (system_protect),
        .dcache_clean       (dcache_clean),
        .dcache_flush       (dcache_flush),
        .icache_flush       (icache_flush),
        .tlb_flush          (tlb_flush),
        .cpu_id             (cpu_id),
        .cache_type         (cache_type),
        .debug_mode         (debug_mode),
        .cp15_reg_out       (cp15_reg_out)
    );
    
    // Clock generation
    initial begin
        clk = 0;
        forever #5 clk = ~clk;
    end
    
    // Helper tasks
    task automatic mrc(input [3:0] crn, input [3:0] crm, input [2:0] op1, input [2:0] op2, output [31:0] data);
        @(posedge clk);
        cp_en = 1;
        cp_op = CP_MRC;
        cp_num = 15;  // CP15
        cp_crn = crn;
        cp_crm = crm;
        cp_op1 = op1;
        cp_op2 = op2;
        cp_data_in = 0;
        @(posedge clk);
        data = cp_data_out;
        cp_en = 0;
        @(posedge clk);
    endtask
    
    task automatic mcr(input [3:0] crn, input [3:0] crm, input [2:0] op1, input [2:0] op2, input [31:0] data);
        @(posedge clk);
        cp_en = 1;
        cp_op = CP_MCR;
        cp_num = 15;  // CP15
        cp_crn = crn;
        cp_crm = crm;
        cp_op1 = op1;
        cp_op2 = op2;
        cp_data_in = data;
        @(posedge clk);
        cp_en = 0;
        @(posedge clk);
    endtask
    
    // Test CPU ID register
    task test_cpu_id();
        logic [31:0] id;
        logic test_passed;
        
        tests_run++;
        $display("\n=== Testing CPU ID Register ===");
        
        // Read CPU ID (c0, c0, 0, 0)
        mrc(0, 0, 0, 0, id);
        
        test_passed = (id == 32'h41007000);  // ARM7TDMI ID
        
        if (test_passed) begin
            tests_passed++;
            $display("✅ CPU ID test PASSED: 0x%08X", id);
        end else begin
            $display("❌ CPU ID test FAILED: expected 0x41007000, got 0x%08X", id);
        end
    endtask
    
    // Test control register
    task test_control_register();
        logic [31:0] ctrl_write, ctrl_read;
        logic test_passed;
        
        tests_run++;
        $display("\n=== Testing Control Register ===");
        
        // Write control register
        ctrl_write = 32'h00003005;  // Enable MMU, D-cache, I-cache
        mcr(1, 0, 0, 0, ctrl_write);
        
        // Read back
        mrc(1, 0, 0, 0, ctrl_read);
        
        // Check system outputs
        test_passed = (ctrl_read[13:0] == ctrl_write[13:0]) &&
                      mmu_enable && 
                      dcache_enable && 
                      icache_enable;
        
        if (test_passed) begin
            tests_passed++;
            $display("✅ Control register test PASSED");
            $display("   MMU=%b, D-cache=%b, I-cache=%b", mmu_enable, dcache_enable, icache_enable);
        end else begin
            $display("❌ Control register test FAILED");
            $display("   Written: 0x%08X, Read: 0x%08X", ctrl_write, ctrl_read);
        end
    endtask
    
    // Test translation table base
    task test_ttb_register();
        logic [31:0] ttb_write, ttb_read;
        logic test_passed;
        
        tests_run++;
        $display("\n=== Testing Translation Table Base ===");
        
        // Write TTB
        ttb_write = 32'h80000000;  // TTB at 0x80000000
        mcr(2, 0, 0, 0, ttb_write);
        
        // Read back
        mrc(2, 0, 0, 0, ttb_read);
        
        test_passed = (ttb_read == ttb_write) && (ttb_base == ttb_write);
        
        if (test_passed) begin
            tests_passed++;
            $display("✅ TTB register test PASSED: 0x%08X", ttb_read);
        end else begin
            $display("❌ TTB register test FAILED");
            $display("   Written: 0x%08X, Read: 0x%08X", ttb_write, ttb_read);
        end
    endtask
    
    // Test cache operations
    task test_cache_operations();
        logic test_passed;
        
        tests_run++;
        $display("\n=== Testing Cache Operations ===");
        
        test_passed = 1;
        
        // Test I-cache flush
        @(posedge clk);
        mcr(7, 5, 0, 0, 0);  // Flush I-cache
        @(posedge clk);
        if (!icache_flush) begin
            $display("❌ I-cache flush failed");
            test_passed = 0;
        end
        @(posedge clk);
        if (icache_flush) begin
            $display("❌ I-cache flush signal not cleared");
            test_passed = 0;
        end
        
        // Test D-cache flush
        @(posedge clk);
        mcr(7, 6, 0, 0, 0);  // Flush D-cache
        @(posedge clk);
        if (!dcache_flush) begin
            $display("❌ D-cache flush failed");
            test_passed = 0;
        end
        
        // Test D-cache clean
        @(posedge clk);
        mcr(7, 10, 0, 1, 0);  // Clean D-cache
        @(posedge clk);
        if (!dcache_clean) begin
            $display("❌ D-cache clean failed");
            test_passed = 0;
        end
        
        if (test_passed) begin
            tests_passed++;
            $display("✅ Cache operations test PASSED");
        end else begin
            $display("❌ Cache operations test FAILED");
        end
    endtask
    
    // Test coprocessor absent
    task test_coprocessor_absent();
        logic [31:0] data;
        logic test_passed;
        
        tests_run++;
        $display("\n=== Testing Coprocessor Absent ===");
        
        // Try to access CP14 (should be absent)
        @(posedge clk);
        cp_en = 1;
        cp_op = CP_MRC;
        cp_num = 14;  // CP14 (not present)
        cp_crn = 0;
        cp_crm = 0;
        cp_op1 = 0;
        cp_op2 = 0;
        @(posedge clk);
        
        test_passed = cp_absent && !cp_busy;
        
        cp_en = 0;
        @(posedge clk);
        
        if (test_passed) begin
            tests_passed++;
            $display("✅ Coprocessor absent test PASSED");
        end else begin
            $display("❌ Coprocessor absent test FAILED");
        end
    endtask
    
    // Main test sequence
    initial begin
        $dumpfile("coprocessor_test_tb.vcd");
        $dumpvars(0, coprocessor_test_tb);
        
        // Initialize
        rst_n = 0;
        cp_en = 0;
        cp_op = CP_MRC;
        cp_num = 15;
        cp_crn = 0;
        cp_crm = 0;
        cp_op1 = 0;
        cp_op2 = 0;
        cp_data_in = 0;
        
        repeat(5) @(posedge clk);
        rst_n = 1;
        repeat(5) @(posedge clk);
        
        $display("=== ARM7TDMI Coprocessor (CP15) Test ===\n");
        
        // Run tests
        test_cpu_id();
        test_control_register();
        test_ttb_register();
        test_cache_operations();
        test_coprocessor_absent();
        
        // Test summary
        repeat(10) @(posedge clk);
        $display("\n=== Test Summary ===");
        $display("Tests Run:    %0d", tests_run);
        $display("Tests Passed: %0d", tests_passed);
        $display("Pass Rate:    %0.1f%%", (tests_passed * 100.0) / tests_run);
        
        if (tests_passed == tests_run) begin
            $display("✅ ALL COPROCESSOR TESTS PASSED!");
        end else begin
            $display("❌ SOME COPROCESSOR TESTS FAILED");
        end
        
        $finish;
    end

endmodule

sim/coprocessor_test_tb.vcd
$date
	Sat Jul 26 12:19:30 2025
$end
$version
	Icarus Verilog
$end
$timescale
	1ps
$end
$scope module coprocessor_test_tb $end
$var wire 32 ! cache_type [31:0] $end
$var wire 1 " cp_busy $end
$var wire 32 # cpu_id [31:0] $end
$var wire 1 $ write_buffer_en $end
$var wire 2 % ttb_ctrl [1:0] $end
$var wire 32 & ttb_base [31:0] $end
$var wire 1 ' tlb_flush $end
$var wire 1 ( system_protect $end
$var wire 1 ) rom_protection $end
$var wire 1 * mmu_enable $end
$var wire 1 + icache_flush $end
$var wire 1 , icache_enable $end
$var wire 1 - high_vectors $end
$var wire 32 . domain_access [31:0] $end
$var wire 1 / dcache_flush $end
$var wire 1 0 dcache_enable $end
$var wire 1 1 dcache_clean $end
$var wire 32 2 cp_data_out [31:0] $end
$var wire 1 3 cp_absent $end
$var wire 32 4 cp15_reg_out [31:0] $end
$var reg 1 5 clk $end
$var reg 4 6 cp_crm [3:0] $end
$var reg 4 7 cp_crn [3:0] $end
$var reg 32 8 cp_data_in [31:0] $end
$var reg 1 9 cp_en $end
$var reg 4 : cp_num [3:0] $end
$var reg 3 ; cp_op [2:0] $end
$var reg 3 < cp_op1 [2:0] $end
$var reg 3 = cp_op2 [2:0] $end
$var reg 1 > debug_mode $end
$var reg 1 ? rst_n $end
$var integer 32 @ tests_passed [31:0] $end
$var integer 32 A tests_run [31:0] $end
$scope module u_coprocessor $end
$var wire 32 B cache_type [31:0] $end
$var wire 1 5 clk $end
$var wire 1 3 cp_absent $end
$var wire 1 " cp_busy $end
$var wire 4 C cp_crm [3:0] $end
$var wire 4 D cp_crn [3:0] $end
$var wire 32 E cp_data_in [31:0] $end
$var wire 1 9 cp_en $end
$var wire 4 F cp_num [3:0] $end
$var wire 3 G cp_op [2:0] $end
$var wire 3 H cp_op1 [2:0] $end
$var wire 3 I cp_op2 [2:0] $end
$var wire 32 J cpu_id [31:0] $end
$var wire 1 1 dcache_clean $end
$var wire 1 0 dcache_enable $end
$var wire 1 / dcache_flush $end
$var wire 1 > debug_mode $end
$var wire 32 K domain_access [31:0] $end
$var wire 1 - high_vectors $end
$var wire 1 , icache_enable $end
$var wire 1 + icache_flush $end
$var wire 1 * mmu_enable $end
$var wire 1 ) rom_protection $end
$var wire 1 ? rst_n $end
$var wire 1 ( system_protect $end
$var wire 1 ' tlb_flush $end
$var wire 32 L ttb_base [31:0] $end
$var wire 1 $ write_buffer_en $end
$var wire 2 M ttb_ctrl [1:0] $end
$var wire 32 N cp15_reg_out [31:0] $end
$var reg 32 O cp_data_out [31:0] $end
$var reg 1 P ctrl_a $end
$var reg 1 Q ctrl_c $end
$var reg 1 R ctrl_i $end
$var reg 1 S ctrl_m $end
$var reg 1 T ctrl_r $end
$var reg 1 U ctrl_s $end
$var reg 1 V ctrl_v $end
$var reg 1 W ctrl_z $end
$var reg 1 X dcache_clean_delayed $end
$var reg 1 Y dcache_clean_trigger $end
$var reg 1 Z dcache_flush_delayed $end
$var reg 1 [ dcache_flush_trigger $end
$var reg 32 \ domain_access_ctrl [31:0] $end
$var reg 32 ] fault_address [31:0] $end
$var reg 32 ^ fault_status [31:0] $end
$var reg 1 _ icache_flush_delayed $end
$var reg 1 ` icache_flush_trigger $end
$var reg 32 a process_id [31:0] $end
$var reg 1 b tlb_flush_delayed $end
$var reg 1 c tlb_flush_trigger $end
$var reg 32 d translation_table_base [31:0] $end
$upscope $end
$scope task mcr $end
$upscope $end
$scope task mrc $end
$upscope $end
$scope task test_cache_operations $end
$var reg 1 e test_passed $end
$upscope $end
$scope task test_control_register $end
$var reg 32 f ctrl_read [31:0] $end
$var reg 32 g ctrl_write [31:0] $end
$var reg 1 h test_passed $end
$upscope $end
$scope task test_coprocessor_absent $end
$var reg 1 i test_passed $end
$upscope $end
$scope task test_cpu_id $end
$var reg 32 j id [31:0] $end
$var reg 1 k test_passed $end
$upscope $end
$scope task test_ttb_register $end
$var reg 1 l test_passed $end
$var reg 32 m ttb_read [31:0] $end
$var reg 32 n ttb_write [31:0] $end
$upscope $end
$upscope $end
$enddefinitions $end
#0
$dumpvars
bx n
bx m
xl
xk
bx j
xi
xh
bx g
bx f
xe
b0 d
0c
0b
b0 a
0`
0_
b0 ^
b0 ]
b0 \
0[
0Z
0Y
0X
0W
0V
0U
0T
0S
0R
0Q
0P
b0 O
b0 N
b0 M
b0 L
b0 K
b1000001000000000111000000000000 J
b0 I
b0 H
b100 G
b1111 F
b0 E
b0 D
b0 C
b1111000000000010000000000010 B
b0 A
b0 @
0?
0>
b0 =
b0 <
b100 ;
b1111 :
09
b0 8
b0 7
b0 6
05
b0 4
03
b0 2
01
00
0/
b0 .
0-
0,
0+
0*
0)
0(
0'
b0 &
b0 %
0$
b1000001000000000111000000000000 #
0"
b1111000000000010000000000010 !
$end
#5000
15
#10000
05
#15000
15
#20000
05
#25000
15
#30000
05
#35000
15
#40000
05
#45000
1?
15
#50000
05
#55000
15
#60000
05
#65000
15
#70000
05
#75000
15
#80000
05
#85000
15
#90000
05
#95000
b1 A
15
#100000
05
#105000
b1000001000000000111000000000000 2
b1000001000000000111000000000000 O
19
15
#110000
05
#115000
b0 2
b0 O
09
15
#120000
05
#125000
b11000000000101 g
b10 A
b1 @
1k
b1000001000000000111000000000000 j
15
#130000
05
#135000
1-
1V
1,
1R
1$
10
1Q
b11000000000101 4
b11000000000101 N
1*
1S
b11000000000101 8
b11000000000101 E
b1 7
b1 D
b11 ;
b11 G
19
15
#140000
05
#145000
09
15
#150000
05
#155000
15
#160000
05
#165000
b11000000000101 2
b11000000000101 O
b0 8
b0 E
b100 ;
b100 G
19
15
#170000
05
#175000
b0 2
b0 O
09
15
#180000
05
#185000
b10000000000000000000000000000000 n
b11 A
b10 @
1h
b11000000000101 f
15
#190000
05
#195000
b10000000000000000000000000000000 &
b10000000000000000000000000000000 L
b10000000000000000000000000000000 d
b10000000000000000000000000000000 8
b10000000000000000000000000000000 E
b10 7
b10 D
b11 ;
b11 G
19
15
#200000
05
#205000
09
15
#210000
05
#215000
15
#220000
05
#225000
b10000000000000000000000000000000 2
b10000000000000000000000000000000 O
b0 8
b0 E
b100 ;
b100 G
19
15
#230000
05
#235000
b0 2
b0 O
09
15
#240000
05
#245000
1e
b100 A
b11 @
1l
b10000000000000000000000000000000 m
15
#250000
05
#255000
15
#260000
05
#265000
1`
b101 6
b101 C
b111 7
b111 D
b11 ;
b11 G
19
15
#270000
05
#275000
1+
1_
0`
09
15
#280000
05
#285000
0+
0_
15
#290000
05
#295000
0e
15
#300000
05
#305000
15
#310000
05
#315000
15
#320000
05
#325000
1[
b110 6
b110 C
19
15
#330000
05
#335000
1/
1Z
0[
09
15
#340000
05
#345000
0/
0Z
15
#350000
05
#355000
15
#360000
05
#365000
15
#370000
05
#375000
1Y
b1 =
b1 I
b1010 6
b1010 C
19
15
#380000
05
#385000
11
1X
0Y
09
15
#390000
05
#395000
01
0X
15
#400000
05
#405000
b101 A
15
#410000
05
#415000
13
b0 2
b0 O
b0 =
b0 I
b0 6
b0 C
b0 7
b0 D
b1110 :
b1110 F
b100 ;
b100 G
19
15
#420000
05
#425000
03
09
1i
15
#430000
05
#435000
b100 @
15
