rtl/arm7tdmi_jtag_tap.sv
// ARM7TDMI JTAG TAP Controller
// Implements IEEE 1149.1 JTAG Test Access Port
`timescale 1ns/1ps

module arm7tdmi_jtag_tap (
    // JTAG pins
    input  logic        tck,        // Test clock
    input  logic        tms,        // Test mode select  
    input  logic        tdi,        // Test data in
    output logic        tdo,        // Test data out
    input  logic        trst_n,     // Test reset (optional)
    
    // TAP controller state outputs
    output logic        test_logic_reset,
    output logic        run_test_idle,
    output logic        select_dr_scan,
    output logic        capture_dr,
    output logic        shift_dr,
    output logic        exit1_dr,
    output logic        pause_dr,
    output logic        exit2_dr,
    output logic        update_dr,
    output logic        select_ir_scan,
    output logic        capture_ir,
    output logic        shift_ir,
    output logic        exit1_ir,
    output logic        pause_ir,
    output logic        exit2_ir,
    output logic        update_ir,
    
    // Chain selection outputs
    output logic        bypass_select,
    output logic        idcode_select,
    output logic        ice_select,
    output logic        scan_n_select,
    
    // Data from external scan chains only
    input  logic        ice_tdo,
    input  logic        scan_n_tdo,
    
    // Current instruction register value
    output logic [3:0]  current_ir
);

    // JTAG TAP Controller State Machine (IEEE 1149.1)
    // Using localparam instead of enum for Icarus Verilog compatibility
    localparam TEST_LOGIC_RESET = 4'h0;
    localparam RUN_TEST_IDLE    = 4'h1;
    localparam SELECT_DR_SCAN   = 4'h2;
    localparam CAPTURE_DR       = 4'h3;
    localparam SHIFT_DR         = 4'h4;
    localparam EXIT1_DR         = 4'h5;
    localparam PAUSE_DR         = 4'h6;
    localparam EXIT2_DR         = 4'h7;
    localparam UPDATE_DR        = 4'h8;
    localparam SELECT_IR_SCAN   = 4'h9;
    localparam CAPTURE_IR       = 4'hA;
    localparam SHIFT_IR         = 4'hB;
    localparam EXIT1_IR         = 4'hC;
    localparam PAUSE_IR         = 4'hD;
    localparam EXIT2_IR         = 4'hE;
    localparam UPDATE_IR        = 4'hF;
    
    logic [3:0] tap_state, tap_next_state;
    
    // ARM7TDMI JTAG Instructions (4-bit)
    localparam EXTEST    = 4'b0000;  // External test
    localparam SCAN_N    = 4'b0010;  // Scan chain select
    localparam SAMPLE    = 4'b0011;  // Sample/preload
    localparam RESTART   = 4'b0100;  // Restart
    localparam CLAMP     = 4'b0101;  // Clamp
    localparam HIGHZ     = 4'b0111;  // High impedance
    localparam CLAMPZ    = 4'b1001;  // Clamp with high-Z
    localparam INTEST    = 4'b1100;  // Internal test
    localparam IDCODE    = 4'b1110;  // ID code
    localparam BYPASS    = 4'b1111;  // Bypass
    
    // Instruction register and data register
    logic [3:0] instruction_reg;
    logic [3:0] ir_shift_reg;
    logic       bypass_reg;
    
    // ARM7TDMI ID Code (32-bit)
    // Format: Version[31:28] | PartNumber[27:12] | ManufacturerID[11:1] | 1'b1
    localparam ARM7TDMI_IDCODE = 32'h07926041; // Example ARM7TDMI ID
    logic [31:0] idcode_shift_reg;
    
    //===========================================
    // TAP Controller State Machine
    //===========================================
    
    always_ff @(posedge tck or negedge trst_n) begin
        if (!trst_n) begin
            tap_state <= TEST_LOGIC_RESET;
        end else begin
            if (tap_state != tap_next_state) begin
                $display("TAP: State %1X -> %1X", tap_state, tap_next_state);
            end
            tap_state <= tap_next_state;
        end
    end
    
    // TAP state machine next state logic
    always_comb begin
        case (tap_state)
            TEST_LOGIC_RESET: begin
                tap_next_state = tms ? TEST_LOGIC_RESET : RUN_TEST_IDLE;
            end
            
            RUN_TEST_IDLE: begin
                tap_next_state = tms ? SELECT_DR_SCAN : RUN_TEST_IDLE;
            end
            
            SELECT_DR_SCAN: begin
                tap_next_state = tms ? SELECT_IR_SCAN : CAPTURE_DR;
            end
            
            CAPTURE_DR: begin
                tap_next_state = tms ? EXIT1_DR : SHIFT_DR;
            end
            
            SHIFT_DR: begin
                tap_next_state = tms ? EXIT1_DR : SHIFT_DR;
            end
            
            EXIT1_DR: begin
                tap_next_state = tms ? UPDATE_DR : PAUSE_DR;
            end
            
            PAUSE_DR: begin
                tap_next_state = tms ? EXIT2_DR : PAUSE_DR;
            end
            
            EXIT2_DR: begin
                tap_next_state = tms ? UPDATE_DR : SHIFT_DR;
            end
            
            UPDATE_DR: begin
                tap_next_state = tms ? SELECT_DR_SCAN : RUN_TEST_IDLE;
            end
            
            SELECT_IR_SCAN: begin
                tap_next_state = tms ? TEST_LOGIC_RESET : CAPTURE_IR;
            end
            
            CAPTURE_IR: begin
                tap_next_state = tms ? EXIT1_IR : SHIFT_IR;
            end
            
            SHIFT_IR: begin
                tap_next_state = tms ? EXIT1_IR : SHIFT_IR;
            end
            
            EXIT1_IR: begin
                tap_next_state = tms ? UPDATE_IR : PAUSE_IR;
            end
            
            PAUSE_IR: begin
                tap_next_state = tms ? EXIT2_IR : PAUSE_IR;
            end
            
            EXIT2_IR: begin
                tap_next_state = tms ? UPDATE_IR : SHIFT_IR;
            end
            
            UPDATE_IR: begin
                tap_next_state = tms ? SELECT_DR_SCAN : RUN_TEST_IDLE;
            end
            
            default: begin
                tap_next_state = TEST_LOGIC_RESET;
            end
        endcase
    end
    
    //===========================================
    // State Output Assignments
    //===========================================
    
    assign test_logic_reset = (tap_next_state == TEST_LOGIC_RESET);
    assign run_test_idle    = (tap_next_state == RUN_TEST_IDLE);
    assign select_dr_scan   = (tap_next_state == SELECT_DR_SCAN);
    assign capture_dr       = (tap_next_state == CAPTURE_DR);
    assign shift_dr         = (tap_next_state == SHIFT_DR);
    assign exit1_dr         = (tap_next_state == EXIT1_DR);
    assign pause_dr         = (tap_next_state == PAUSE_DR);
    assign exit2_dr         = (tap_next_state == EXIT2_DR);
    assign update_dr        = (tap_next_state == UPDATE_DR);
    assign select_ir_scan   = (tap_next_state == SELECT_IR_SCAN);
    assign capture_ir       = (tap_next_state == CAPTURE_IR);
    assign shift_ir         = (tap_next_state == SHIFT_IR);
    assign exit1_ir         = (tap_next_state == EXIT1_IR);
    assign pause_ir         = (tap_next_state == PAUSE_IR);
    assign exit2_ir         = (tap_next_state == EXIT2_IR);
    assign update_ir        = (tap_next_state == UPDATE_IR);
    
    //===========================================
    // Instruction Register
    //===========================================
    
    always_ff @(posedge tck or negedge trst_n) begin
        if (!trst_n) begin
            instruction_reg <= IDCODE;  // Default to IDCODE on reset
            ir_shift_reg <= 4'b0;
        end else begin
            if (update_ir) begin
                // Update instruction register
                instruction_reg <= ir_shift_reg;
                $display("TAP: Updating IR to 0x%1X (state=%1X)", ir_shift_reg, tap_state);
            end else if (capture_ir) begin
                // Capture pattern: 4'b0001 (ARM specification)
                ir_shift_reg <= 4'b0001;
                $display("TAP: Capturing IR pattern 0x1");
            end else if (shift_ir) begin
                // Shift instruction register
                ir_shift_reg <= {tdi, ir_shift_reg[3:1]};
                $display("TAP: Shifting IR: TDI=%b, ir_shift_reg=0x%1X -> 0x%1X (state=%1X)", tdi, ir_shift_reg, {tdi, ir_shift_reg[3:1]}, tap_state);
            end
        end
    end
    
    assign current_ir = instruction_reg;
    
    //===========================================
    // Chain Selection Logic
    //===========================================
    
    always_comb begin
        // Default all chains deselected
        bypass_select = 1'b0;
        idcode_select = 1'b0;
        ice_select = 1'b0;
        scan_n_select = 1'b0;
        
        // Select chain based on current instruction
        case (instruction_reg)
            BYPASS: bypass_select = 1'b1;
            IDCODE: idcode_select = 1'b1;
            INTEST: begin
                ice_select = 1'b1;      // EmbeddedICE chain
                $display("TAP: INTEST instruction active, ice_select=1");
            end
            SCAN_N: scan_n_select = 1'b1;
            default: bypass_select = 1'b1;  // Default to bypass
        endcase
    end
    
    //===========================================
    // Data Registers
    //===========================================
    
    // Bypass register (1-bit) - simple delay register
    always_ff @(posedge tck or negedge trst_n) begin
        if (!trst_n) begin
            bypass_reg <= 1'b0;
        end else if (shift_dr && bypass_select) begin
            bypass_reg <= tdi;
        end else if (capture_dr && bypass_select) begin
            bypass_reg <= 1'b0;  // Capture fixed value
        end
    end
    
    // IDCODE register (32-bit)
    always_ff @(posedge tck or negedge trst_n) begin
        if (!trst_n) begin
            idcode_shift_reg <= ARM7TDMI_IDCODE;
        end else if (capture_dr && idcode_select) begin
            idcode_shift_reg <= ARM7TDMI_IDCODE;
        end else if (shift_dr && idcode_select) begin
            idcode_shift_reg <= {tdi, idcode_shift_reg[31:1]};
        end
    end
    
    //===========================================
    // TDO Output Multiplexer
    //===========================================
    
    always_comb begin
        if (shift_ir) begin
            // Shifting instruction register
            tdo = ir_shift_reg[0];
        end else if (shift_dr) begin
            // Shifting data register - select based on active chain
            if (bypass_select) begin
                tdo = bypass_reg;
            end else if (idcode_select) begin
                tdo = idcode_shift_reg[0];
            end else if (ice_select) begin
                tdo = ice_tdo;
            end else if (scan_n_select) begin
                tdo = scan_n_tdo;
            end else begin
                tdo = bypass_reg;  // Default to bypass
            end
        end else begin
            tdo = 1'b0;
        end
    end
    
endmodule

sim/debug_tap_ir.sv
// Debug TAP IR loading issue
`timescale 1ns/1ps

module debug_tap_ir;

    logic tck = 0;
    logic tms = 0; 
    logic tdi = 0;
    logic tdo;
    logic trst_n = 1;
    logic [3:0] current_ir;

    always #10 tck = ~tck;

    arm7tdmi_jtag_tap u_tap (
        .tck(tck),
        .tms(tms),
        .tdi(tdi),
        .tdo(tdo),
        .trst_n(trst_n),
        .test_logic_reset(),
        .run_test_idle(),
        .select_dr_scan(),
        .capture_dr(),
        .shift_dr(),
        .exit1_dr(),
        .pause_dr(),
        .exit2_dr(),
        .update_dr(),
        .select_ir_scan(),
        .capture_ir(),
        .shift_ir(),
        .exit1_ir(),
        .pause_ir(),
        .exit2_ir(),
        .update_ir(),
        .bypass_select(),
        .idcode_select(),
        .ice_select(),
        .scan_n_select(),
        .ice_tdo(1'b0),
        .scan_n_tdo(1'b0),
        .current_ir(current_ir)
    );

    initial begin
        $dumpfile("debug_tap_ir.vcd");
        $dumpvars(0, debug_tap_ir);
        
        // Reset
        trst_n = 0;
        repeat(5) @(posedge tck);
        trst_n = 1;
        repeat(2) @(posedge tck);
        
        $display("=== Debug TAP IR Loading ==.");
        
        // Reset TAP 
        tms = 1;
        repeat(6) @(posedge tck);
        tms = 0;
        @(posedge tck);
        
        $display("After reset: current_ir=0x%1X", current_ir);
        $display("Internal state: instruction_reg=0x%1X, ir_shift_reg=0x%1X", 
                 u_tap.instruction_reg, u_tap.ir_shift_reg);
        
        // Load INTEST instruction (0xC = 1100 binary)
        $display("\nLoading INTEST instruction (0xC = 1100)...");
        
        // Go to Select-IR-Scan
        $display("RUN_TEST_IDLE -> SELECT_DR_SCAN");
        tms = 1; @(posedge tck);
        $display("SELECT_DR_SCAN -> SELECT_IR_SCAN");
        tms = 1; @(posedge tck);
        
        // Capture-IR
        $display("SELECT_IR_SCAN -> CAPTURE_IR");
        tms = 0; @(posedge tck);
        #1; // Small delay to let signals settle
        $display("After CAPTURE_IR: ir_shift_reg=0x%1X", u_tap.ir_shift_reg);
        
        // Shift-IR - shift in 0xC (LSB first: 0,0,1,1)
        $display("CAPTURE_IR -> SHIFT_IR");
        tdi = 0; tms = 0; @(posedge tck); // Bit 0
        $display("After bit 0=0: ir_shift_reg=0x%1X", u_tap.ir_shift_reg);
        
        tdi = 0; tms = 0; @(posedge tck); // Bit 1
        $display("After bit 1=0: ir_shift_reg=0x%1X", u_tap.ir_shift_reg);
        
        tdi = 1; tms = 0; @(posedge tck); // Bit 2  
        $display("After bit 2=1: ir_shift_reg=0x%1X", u_tap.ir_shift_reg);
        
        tdi = 1; tms = 1; @(posedge tck); // Bit 3, exit
        $display("After bit 3=1 (exit): ir_shift_reg=0x%1X", u_tap.ir_shift_reg);
        
        // Exit1-IR -> Update-IR
        $display("EXIT1_IR -> UPDATE_IR");
        tms = 1; @(posedge tck);
        $display("After UPDATE_IR: instruction_reg=0x%1X, ir_shift_reg=0x%1X", 
                 u_tap.instruction_reg, u_tap.ir_shift_reg);
        
        // Update-IR -> Run-Test/Idle
        $display("UPDATE_IR -> RUN_TEST_IDLE");
        tms = 0; @(posedge tck);
        
        $display("\nFinal state: current_ir=0x%1X", current_ir);
        $display("Expected: 0xC, Got: 0x%1X", current_ir);
        
        if (current_ir == 4'hC) begin
            $display("✅ INTEST instruction loaded correctly!");
        end else begin
            $display("❌ INTEST instruction failed!");
        end
        
        $finish;
    end

endmodule

sim/debug_tap_ir.vcd
$date
	Sat Jul 26 06:34:11 2025
$end
$version
	Icarus Verilog
$end
$timescale
	1ps
$end
$scope module debug_tap_ir $end
$var wire 1 ! tdo $end
$var wire 4 " current_ir [3:0] $end
$var reg 1 # tck $end
$var reg 1 $ tdi $end
$var reg 1 % tms $end
$var reg 1 & trst_n $end
$scope module u_tap $end
$var wire 4 ' current_ir [3:0] $end
$var wire 1 ( ice_tdo $end
$var wire 1 ) scan_n_tdo $end
$var wire 1 # tck $end
$var wire 1 $ tdi $end
$var wire 1 % tms $end
$var wire 1 & trst_n $end
$var wire 1 * update_ir $end
$var wire 1 + update_dr $end
$var wire 1 , test_logic_reset $end
$var wire 1 - shift_ir $end
$var wire 1 . shift_dr $end
$var wire 1 / select_ir_scan $end
$var wire 1 0 select_dr_scan $end
$var wire 1 1 run_test_idle $end
$var wire 1 2 pause_ir $end
$var wire 1 3 pause_dr $end
$var wire 1 4 exit2_ir $end
$var wire 1 5 exit2_dr $end
$var wire 1 6 exit1_ir $end
$var wire 1 7 exit1_dr $end
$var wire 1 8 capture_ir $end
$var wire 1 9 capture_dr $end
$var reg 1 : bypass_reg $end
$var reg 1 ; bypass_select $end
$var reg 1 < ice_select $end
$var reg 1 = idcode_select $end
$var reg 32 > idcode_shift_reg [31:0] $end
$var reg 4 ? instruction_reg [3:0] $end
$var reg 4 @ ir_shift_reg [3:0] $end
$var reg 1 A scan_n_select $end
$var reg 4 B tap_next_state [3:0] $end
$var reg 4 C tap_state [3:0] $end
$var reg 1 ! tdo $end
$upscope $end
$upscope $end
$enddefinitions $end
#0
$dumpvars
b0 C
b1 B
0A
b0 @
b1110 ?
b111100100100110000001000001 >
1=
0<
0;
0:
09
08
07
06
05
04
03
02
11
00
0/
0.
0-
0,
0+
0*
0)
0(
b1110 '
0&
0%
0$
0#
b1110 "
0!
$end
#10000
1#
#20000
0#
#30000
1#
#40000
0#
#50000
1#
#60000
0#
#70000
1#
#80000
0#
#90000
b1 C
1&
1#
#100000
0#
#110000
1#
#120000
0#
#130000
01
10
b10 B
1%
1#
#140000
0#
#150000
00
1/
b1001 B
b10 C
1#
#160000
0#
#170000
1,
0/
b0 B
b1001 C
1#
#180000
0#
#190000
b0 C
1#
#200000
0#
#210000
1#
#220000
0#
#230000
1#
#240000
0#
#250000
0,
11
b1 B
0%
1#
#260000
0#
#270000
10
b1 C
0,
01
b10 B
1%
1#
#280000
0#
#290000
00
1/
b1001 B
b10 C
1#
#300000
0#
#310000
18
b1001 C
09
0/
b1010 B
0%
1#
#320000
0#
#330000
1=
1!
08
1-
b1011 B
b1 @
b1010 C
1#
#340000
0#
#350000
1=
0!
b1011 C
b0 @
1#
#360000
0#
#370000
1=
b1000 @
1$
1#
#380000
0#
#390000
b1100 @
1=
0-
16
b1100 B
1%
1#
#400000
0#
#410000
06
1*
b1111 B
b1100 C
1#
#420000
0#
#430000
11
1<
0=
b1111 C
b1100 "
b1100 '
b1100 ?
02
0*
b1 B
0%
1#
#440000
0#
#450000
1#
