rtl/arm7tdmi_multiply.sv
import arm7tdmi_pkg::*;

module arm7tdmi_multiply (
    input  logic        clk,
    input  logic        rst_n,
    
    // Control signals
    input  logic        mul_en,
    input  logic        mul_long,
    input  logic        mul_signed,
    input  logic        mul_accumulate,
    input  logic        mul_set_flags,
    input  logic [1:0]  mul_type,         // 00=MUL, 01=MLA, 10=UMULL/SMULL, 11=UMLAL/SMLAL
    
    // Operands
    input  logic [31:0] operand_a,
    input  logic [31:0] operand_b,
    input  logic [31:0] acc_hi,     // For accumulate operations
    input  logic [31:0] acc_lo,
    
    // Results
    output logic [31:0] result_hi,
    output logic [31:0] result_lo,
    output logic        result_ready,
    
    // Flags
    output logic        negative,
    output logic        zero
);

    // Multiply operation types
    typedef enum logic [1:0] {
        MUL_TYPE_MUL    = 2'b00,  // MUL - 32x32->32
        MUL_TYPE_MLA    = 2'b01,  // MLA - 32x32+32->32
        MUL_TYPE_MULL   = 2'b10,  // UMULL/SMULL - 32x32->64
        MUL_TYPE_MLAL   = 2'b11   // UMLAL/SMLAL - 32x32+64->64
    } mul_type_t;
    
    // Multiply operation
    logic [63:0] mul_result;
    logic [63:0] final_result;
    
    // Perform multiplication
    always_comb begin
        if (mul_signed) begin
            // Signed multiply
            mul_result = $signed(operand_a) * $signed(operand_b);
        end else begin
            // Unsigned multiply
            mul_result = operand_a * operand_b;
        end
        
        // Handle different multiply types
        case (mul_type)
            MUL_TYPE_MUL: begin
                // MUL: Rd = Rm * Rs
                final_result = {32'b0, mul_result[31:0]};
            end
            
            MUL_TYPE_MLA: begin
                // MLA: Rd = (Rm * Rs) + Rn
                final_result = {32'b0, mul_result[31:0] + acc_lo};
            end
            
            MUL_TYPE_MULL: begin
                // UMULL/SMULL: RdHi:RdLo = Rm * Rs
                final_result = mul_result;
            end
            
            MUL_TYPE_MLAL: begin
                // UMLAL/SMLAL: RdHi:RdLo = (Rm * Rs) + RdHi:RdLo
                final_result = mul_result + {acc_hi, acc_lo};
            end
        endcase
    end
    
    // Output results based on multiply type
    assign result_hi = (mul_type == MUL_TYPE_MULL || mul_type == MUL_TYPE_MLAL) ? 
                      final_result[63:32] : 32'b0;
    assign result_lo = final_result[31:0];
    assign result_ready = mul_en;  // Single cycle multiply for now
    
    // Flags (only updated if mul_set_flags is asserted)
    assign negative = mul_set_flags ? 
                     ((mul_type == MUL_TYPE_MULL || mul_type == MUL_TYPE_MLAL) ? 
                      final_result[63] : final_result[31]) : 1'b0;
    assign zero = mul_set_flags ? 
                 ((mul_type == MUL_TYPE_MULL || mul_type == MUL_TYPE_MLAL) ? 
                  (final_result == 64'b0) : (final_result[31:0] == 32'b0)) : 1'b0;

endmodule

sim/multiply_tb.sv
// Simple multiply testbench
`timescale 1ns/1ps

module multiply_tb;
    
    // Clock and reset
    logic clk = 0;
    logic rst_n = 1;
    
    always #5 clk = ~clk;  // 100MHz clock
    
    // Multiply unit signals
    logic        mul_en;
    logic        mul_long;
    logic        mul_signed;
    logic        mul_accumulate;
    logic        mul_set_flags;
    logic [1:0]  mul_type;
    logic [31:0] operand_a;
    logic [31:0] operand_b;
    logic [31:0] acc_hi;
    logic [31:0] acc_lo;
    logic [31:0] result_hi;
    logic [31:0] result_lo;
    logic        result_ready;
    logic        negative;
    logic        zero;
    
    // Instantiate multiply unit
    arm7tdmi_multiply u_multiply (
        .clk            (clk),
        .rst_n          (rst_n),
        .mul_en         (mul_en),
        .mul_long       (mul_long),
        .mul_signed     (mul_signed),
        .mul_accumulate (mul_accumulate),
        .mul_set_flags  (mul_set_flags),
        .mul_type       (mul_type),
        .operand_a      (operand_a),
        .operand_b      (operand_b),
        .acc_hi         (acc_hi),
        .acc_lo         (acc_lo),
        .result_hi      (result_hi),
        .result_lo      (result_lo),
        .result_ready   (result_ready),
        .negative       (negative),
        .zero           (zero)
    );
    
    initial begin
        $dumpfile("multiply_tb.vcd");
        $dumpvars(0, multiply_tb);
        
        // Reset
        rst_n = 0;
        mul_en = 0;
        mul_long = 0;
        mul_signed = 0;
        mul_accumulate = 0;
        mul_set_flags = 0;
        mul_type = 2'b00;
        operand_a = 32'h0;
        operand_b = 32'h0;
        acc_hi = 32'h0;
        acc_lo = 32'h0;
        
        @(posedge clk);
        rst_n = 1;
        @(posedge clk);
        
        $display("=== ARM7TDMI Multiply Unit Test ===");
        
        // Test 1: Simple MUL (5 * 7 = 35)
        $display("Test 1: MUL - 5 * 7");
        mul_en = 1;
        mul_type = 2'b00;  // MUL
        mul_set_flags = 1;
        operand_a = 32'd5;
        operand_b = 32'd7;
        @(posedge clk);
        if (result_lo == 32'd35) begin
            $display("  PASS: result = %d", result_lo);
        end else begin
            $display("  FAIL: expected 35, got %d", result_lo);
        end
        mul_en = 0;
        @(posedge clk);
        
        // Test 2: MLA (3 * 4 + 2 = 14)
        $display("Test 2: MLA - (3 * 4) + 2");
        mul_en = 1;
        mul_type = 2'b01;  // MLA
        mul_set_flags = 1;
        operand_a = 32'd3;
        operand_b = 32'd4;
        acc_lo = 32'd2;
        @(posedge clk);
        if (result_lo == 32'd14) begin
            $display("  PASS: result = %d", result_lo);
        end else begin
            $display("  FAIL: expected 14, got %d", result_lo);
        end
        mul_en = 0;
        @(posedge clk);
        
        // Test 3: UMULL (0xFFFFFFFF * 0xFFFFFFFF)
        $display("Test 3: UMULL - 0xFFFFFFFF * 0xFFFFFFFF");
        mul_en = 1;
        mul_type = 2'b10;  // UMULL
        mul_signed = 0;
        mul_set_flags = 1;
        operand_a = 32'hFFFFFFFF;
        operand_b = 32'hFFFFFFFF;
        acc_hi = 32'h0;
        acc_lo = 32'h0;
        @(posedge clk);
        $display("  Result: %08h_%08h", result_hi, result_lo);
        if (result_hi == 32'hFFFFFFFE && result_lo == 32'h00000001) begin
            $display("  PASS: UMULL correct");
        end else begin
            $display("  FAIL: expected FFFFFFFE_00000001");
        end
        mul_en = 0;
        @(posedge clk);
        
        // Test 4: SMULL (-1 * -1 = 1)
        $display("Test 4: SMULL - (-1) * (-1)");
        mul_en = 1;
        mul_type = 2'b10;  // SMULL
        mul_signed = 1;
        mul_set_flags = 1;
        operand_a = 32'hFFFFFFFF;  // -1
        operand_b = 32'hFFFFFFFF;  // -1
        @(posedge clk);
        $display("  Result: %08h_%08h", result_hi, result_lo);
        if (result_hi == 32'h00000000 && result_lo == 32'h00000001) begin
            $display("  PASS: SMULL correct");
        end else begin
            $display("  FAIL: expected 00000000_00000001");
        end
        mul_en = 0;
        @(posedge clk);
        
        // Test 5: Zero flag test (0 * anything = 0)
        $display("Test 5: Zero flag test - 0 * 42");
        mul_en = 1;
        mul_type = 2'b00;  // MUL
        mul_set_flags = 1;
        operand_a = 32'd0;
        operand_b = 32'd42;
        @(posedge clk);
        if (result_lo == 32'd0 && zero == 1'b1) begin
            $display("  PASS: result = 0, zero flag set");
        end else begin
            $display("  FAIL: expected 0 with zero flag, got %d, zero=%b", result_lo, zero);
        end
        mul_en = 0;
        
        $display("=== Test Complete ===");
        $finish;
    end
    
endmodule

sim/multiply_tb.vcd
$date
	Thu Jul 24 10:13:13 2025
$end
$version
	Icarus Verilog
$end
$timescale
	1ps
$end
$scope module multiply_tb $end
$var wire 1 ! zero $end
$var wire 1 " result_ready $end
$var wire 32 # result_lo [31:0] $end
$var wire 32 $ result_hi [31:0] $end
$var wire 1 % negative $end
$var reg 32 & acc_hi [31:0] $end
$var reg 32 ' acc_lo [31:0] $end
$var reg 1 ( clk $end
$var reg 1 ) mul_accumulate $end
$var reg 1 * mul_en $end
$var reg 1 + mul_long $end
$var reg 1 , mul_set_flags $end
$var reg 1 - mul_signed $end
$var reg 2 . mul_type [1:0] $end
$var reg 32 / operand_a [31:0] $end
$var reg 32 0 operand_b [31:0] $end
$var reg 1 1 rst_n $end
$scope module u_multiply $end
$var wire 32 2 acc_hi [31:0] $end
$var wire 32 3 acc_lo [31:0] $end
$var wire 1 ( clk $end
$var wire 1 ) mul_accumulate $end
$var wire 1 * mul_en $end
$var wire 1 + mul_long $end
$var wire 1 , mul_set_flags $end
$var wire 1 - mul_signed $end
$var wire 2 4 mul_type [1:0] $end
$var wire 32 5 operand_a [31:0] $end
$var wire 32 6 operand_b [31:0] $end
$var wire 1 " result_ready $end
$var wire 1 1 rst_n $end
$var wire 1 ! zero $end
$var wire 32 7 result_lo [31:0] $end
$var wire 32 8 result_hi [31:0] $end
$var wire 1 % negative $end
$var reg 64 9 final_result [63:0] $end
$var reg 64 : mul_result [63:0] $end
$upscope $end
$upscope $end
$enddefinitions $end
#0
$dumpvars
b0 :
b0 9
b0 8
b0 7
b0 6
b0 5
b0 4
b0 3
b0 2
01
b0 0
b0 /
b0 .
0-
0,
0+
0*
0)
0(
b0 '
b0 &
0%
b0 $
b0 #
0"
0!
$end
#5000
11
1(
#10000
0(
#15000
b100011 #
b100011 7
b100011 9
b100011 :
0!
b111 0
b111 6
b101 /
b101 5
1,
1"
1*
1(
#20000
0(
#25000
0"
0*
1(
#30000
0(
#35000
b1110 #
b1110 7
b1110 9
b1100 :
b10 '
b10 3
b100 0
b100 6
b11 /
b11 5
b1 .
b1 4
1"
1*
1(
#40000
0(
#45000
0"
0*
1(
#50000
0(
#55000
1%
b11111111111111111111111111111110 $
b11111111111111111111111111111110 8
b1 #
b1 7
b1111111111111111111111111111111000000000000000000000000000000001 9
b1111111111111111111111111111111000000000000000000000000000000001 :
b0 '
b0 3
b11111111111111111111111111111111 0
b11111111111111111111111111111111 6
b11111111111111111111111111111111 /
b11111111111111111111111111111111 5
b10 .
b10 4
1"
1*
1(
#60000
0(
#65000
0"
0*
1(
#70000
0(
#75000
0%
b0 $
b0 8
b1 9
b1 :
1-
1"
1*
1(
#80000
0(
#85000
0"
0*
1(
#90000
0(
#95000
1!
b0 #
b0 7
b0 9
b0 :
b101010 0
b101010 6
b0 /
b0 5
b0 .
b0 4
1"
1*
1(
#100000
0(
#105000
0"
0*
1(
