rtl/arm7tdmi_multiply.sv
import arm7tdmi_pkg::*;

module arm7tdmi_multiply (
    input  logic        clk,
    input  logic        rst_n,
    
    // Control signals
    input  logic        mul_en,
    input  logic        mul_long,
    input  logic        mul_signed,
    input  logic        mul_accumulate,
    input  logic        mul_set_flags,
    input  logic [1:0]  mul_type,         // 00=MUL, 01=MLA, 10=UMULL/SMULL, 11=UMLAL/SMLAL
    
    // Operands
    input  logic [31:0] operand_a,
    input  logic [31:0] operand_b,
    input  logic [31:0] acc_hi,     // For accumulate operations
    input  logic [31:0] acc_lo,
    
    // Results
    output logic [31:0] result_hi,
    output logic [31:0] result_lo,
    output logic        result_ready,
    
    // Flags
    output logic        negative,
    output logic        zero
);

    // Multiply operation types
    typedef enum logic [1:0] {
        MUL_TYPE_MUL    = 2'b00,  // MUL - 32x32->32
        MUL_TYPE_MLA    = 2'b01,  // MLA - 32x32+32->32
        MUL_TYPE_MULL   = 2'b10,  // UMULL/SMULL - 32x32->64
        MUL_TYPE_MLAL   = 2'b11   // UMLAL/SMLAL - 32x32+64->64
    } mul_type_t;
    
    // Multiply operation
    logic [63:0] mul_result;
    logic [63:0] final_result;
    logic [63:0] accumulator;
    
    // Addition logic for long multiply accumulate
    logic [32:0] lo_sum;  // 33-bit to catch carry
    logic [31:0] hi_sum;
    logic [63:0] accumulate_result;
    
    // Perform multiplication
    always_comb begin
        if (mul_signed) begin
            // Signed multiply
            mul_result = $signed(operand_a) * $signed(operand_b);
        end else begin
            // Unsigned multiply
            mul_result = operand_a * operand_b;
        end
        
        // Prepare accumulator value
        accumulator = {acc_hi, acc_lo};
        
        // Manual 64-bit addition for accumulate operations
        lo_sum = {1'b0, mul_result[31:0]} + {1'b0, accumulator[31:0]};
        hi_sum = mul_result[63:32] + accumulator[63:32] + lo_sum[32];
        accumulate_result = {hi_sum, lo_sum[31:0]};
        
        // Handle different multiply types
        case (mul_type)
            MUL_TYPE_MUL: begin
                // MUL: Rd = Rm * Rs
                final_result = {32'b0, mul_result[31:0]};
            end
            
            MUL_TYPE_MLA: begin
                // MLA: Rd = (Rm * Rs) + Rn
                final_result = {32'b0, mul_result[31:0] + acc_lo};
            end
            
            MUL_TYPE_MULL: begin
                // UMULL/SMULL: RdHi:RdLo = Rm * Rs
                final_result = mul_result;
            end
            
            MUL_TYPE_MLAL: begin
                // UMLAL/SMLAL: RdHi:RdLo = (Rm * Rs) + RdHi:RdLo
                final_result = accumulate_result;
            end
            
            default: begin
                final_result = 64'b0;
            end
        endcase
    end
    
    // Output results based on multiply type
    assign result_hi = (mul_type == MUL_TYPE_MULL || mul_type == MUL_TYPE_MLAL) ? 
                      final_result[63:32] : 32'b0;
    assign result_lo = final_result[31:0];
    assign result_ready = mul_en;  // Single cycle multiply for now
    
    // Flags (only updated if mul_set_flags is asserted)
    assign negative = mul_set_flags ? 
                     ((mul_type == MUL_TYPE_MULL || mul_type == MUL_TYPE_MLAL) ? 
                      final_result[63] : final_result[31]) : 1'b0;
    assign zero = mul_set_flags ? 
                 ((mul_type == MUL_TYPE_MULL || mul_type == MUL_TYPE_MLAL) ? 
                  (final_result == 64'b0) : (final_result[31:0] == 32'b0)) : 1'b0;

endmodule

sim/multiply_accum_test_tb.sv
// ARM7TDMI Multiply Accumulation Test
// Tests MLA, UMLAL, and SMLAL instructions

`timescale 1ns/1ps

import arm7tdmi_pkg::*;

module multiply_accum_test_tb;
    
    // Clock and reset
    logic clk = 0;
    logic rst_n = 1;
    
    always #5 clk = ~clk;  // 100MHz clock
    
    // Test interface signals
    logic        mul_en;
    logic        mul_long;
    logic        mul_signed;
    logic        mul_accumulate;
    logic        mul_set_flags;
    logic [1:0]  mul_type;
    logic [31:0] operand_a;
    logic [31:0] operand_b;
    logic [31:0] acc_hi;
    logic [31:0] acc_lo;
    logic [31:0] result_hi;
    logic [31:0] result_lo;
    logic        result_ready;
    logic        negative;
    logic        zero;
    
    // Test variables
    int test_count = 0;
    int test_passed = 0;
    
    // DUT instantiation
    arm7tdmi_multiply u_multiply (
        .clk            (clk),
        .rst_n          (rst_n),
        .mul_en         (mul_en),
        .mul_long       (mul_long),
        .mul_signed     (mul_signed),
        .mul_accumulate (mul_accumulate),
        .mul_set_flags  (mul_set_flags),
        .mul_type       (mul_type),
        .operand_a      (operand_a),
        .operand_b      (operand_b),
        .acc_hi         (acc_hi),
        .acc_lo         (acc_lo),
        .result_hi      (result_hi),
        .result_lo      (result_lo),
        .result_ready   (result_ready),
        .negative       (negative),
        .zero           (zero)
    );
    
    // Test task for multiply operations
    task test_multiply(
        input string test_name,
        input logic [2:0] test_type,
        input logic [31:0] a,
        input logic [31:0] b,
        input logic [31:0] acc_h,
        input logic [31:0] acc_l,
        input logic [31:0] exp_hi,
        input logic [31:0] exp_lo
    );
        test_count++;
        $display("\nTest %d: %s", test_count, test_name);
        $display("  A=0x%08X, B=0x%08X", a, b);
        if (test_type == 3'd1 || test_type == 3'd3 || test_type == 3'd5) begin
            $display("  Accumulator: Hi=0x%08X, Lo=0x%08X", acc_h, acc_l);
        end
        
        // Setup multiply operation
        operand_a = a;
        operand_b = b;
        acc_hi = acc_h;
        acc_lo = acc_l;
        mul_type = test_type;
        
        // Decode multiply type
        case (test_type)
            3'd0: begin
                mul_long = 1'b0;
                mul_signed = 1'b0;
                mul_accumulate = 1'b0;
            end
            3'd1: begin
                mul_long = 1'b0;
                mul_signed = 1'b0;
                mul_accumulate = 1'b1;
            end
            3'd2: begin
                mul_long = 1'b1;
                mul_signed = 1'b0;
                mul_accumulate = 1'b0;
            end
            3'd3: begin
                mul_long = 1'b1;
                mul_signed = 1'b0;
                mul_accumulate = 1'b1;
            end
            3'd4: begin
                mul_long = 1'b1;
                mul_signed = 1'b1;
                mul_accumulate = 1'b0;
            end
            3'd5: begin
                mul_long = 1'b1;
                mul_signed = 1'b1;
                mul_accumulate = 1'b1;
            end
        endcase
        
        mul_set_flags = 1'b1;
        mul_en = 1'b1;
        @(posedge clk);
        
        // Wait for result
        wait(result_ready);
        @(posedge clk);
        mul_en = 1'b0;
        
        // Check results
        if (result_hi == exp_hi && result_lo == exp_lo) begin
            test_passed++;
            $display("  ✅ PASS: Result correct");
            $display("    Got: Hi=0x%08X, Lo=0x%08X", result_hi, result_lo);
        end else begin
            $display("  ❌ FAIL: Result incorrect");
            $display("    Expected: Hi=0x%08X, Lo=0x%08X", exp_hi, exp_lo);
            $display("    Got:      Hi=0x%08X, Lo=0x%08X", result_hi, result_lo);
            // Debug info for signed multiply accumulate
            if (test_type == 3'd5) begin
                $display("    Debug: mul_signed=%b, operand_a=%d, operand_b=%d", 
                        u_multiply.mul_signed, $signed(operand_a), $signed(operand_b));
                $display("    Debug: mul_result=0x%016X", u_multiply.mul_result);
                $display("    Debug: accumulator=0x%016X", u_multiply.accumulator);
                $display("    Debug: accumulate_result=0x%016X", u_multiply.accumulate_result);
                $display("    Debug: final_result=0x%016X", u_multiply.final_result);
                $display("    Debug: result_hi assignment = final_result[63:32] = 0x%08X", 
                        u_multiply.final_result[63:32]);
            end
        end
        
        @(posedge clk);
    endtask
    
    // Main test sequence
    initial begin
        $dumpfile("multiply_accum_test_tb.vcd");
        $dumpvars(0, multiply_accum_test_tb);
        
        $display("=== ARM7TDMI Multiply Accumulation Test ===");
        
        // Initialize
        mul_en = 0;
        operand_a = 0;
        operand_b = 0;
        acc_hi = 0;
        acc_lo = 0;
        
        // Reset
        rst_n = 0;
        repeat(5) @(posedge clk);
        rst_n = 1;
        repeat(5) @(posedge clk);
        
        // Test MLA (Multiply Accumulate)
        $display("\n=== MLA Tests ===");
        test_multiply("MLA: 5 * 7 + 10", 3'd1, 
                     32'd5, 32'd7, 32'd0, 32'd10,
                     32'd0, 32'd45);  // 5*7 + 10 = 45
        
        test_multiply("MLA: 100 * 200 + 5000", 3'd1,
                     32'd100, 32'd200, 32'd0, 32'd5000,
                     32'd0, 32'd25000);  // 100*200 + 5000 = 25000
        
        test_multiply("MLA: 0xFFFF * 0xFFFF + 0x10000", 3'd1,
                     32'h0000FFFF, 32'h0000FFFF, 32'd0, 32'h00010000,
                     32'd0, 32'hFFFF0001);  // 65535*65535 + 65536
        
        // Test UMLAL (Unsigned Multiply Accumulate Long)
        $display("\n=== UMLAL Tests ===");
        test_multiply("UMLAL: 0x10000 * 0x10000 + 0", 3'd3,
                     32'h00010000, 32'h00010000, 32'd0, 32'd0,
                     32'h00000001, 32'h00000000);  // 65536*65536 = 0x100000000
        
        test_multiply("UMLAL: 0xFFFFFFFF * 2 + 0x100000001", 3'd3,
                     32'hFFFFFFFF, 32'd2, 32'h00000001, 32'h00000001,
                     32'h00000002, 32'hFFFFFFFF);  // Large accumulation
        
        // Test SMLAL (Signed Multiply Accumulate Long)
        $display("\n=== SMLAL Tests ===");
        test_multiply("SMLAL: -1000 * 1000 + 0", 3'd5,
                     -32'd1000, 32'd1000, 32'd0, 32'd0,
                     32'hFFFFFFFF, -32'd1000000);  // -1000000
        
        test_multiply("SMLAL: -1 * -1 + (-1)", 3'd5,
                     32'hFFFFFFFF, 32'hFFFFFFFF, 32'hFFFFFFFF, 32'hFFFFFFFF,
                     32'd0, 32'd0);  // 1 + (-1) = 0
        
        test_multiply("SMLAL: 0x7FFFFFFF * 2 + 0x100000000", 3'd5,
                     32'h7FFFFFFF, 32'd2, 32'h00000001, 32'h00000000,
                     32'h00000001, 32'hFFFFFFFE);  // Max positive accumulation
        
        // Edge cases
        $display("\n=== Edge Cases ===");
        test_multiply("MLA: 0 * 0 + 0xFFFFFFFF", 3'd1,
                     32'd0, 32'd0, 32'd0, 32'hFFFFFFFF,
                     32'd0, 32'hFFFFFFFF);
        
        test_multiply("UMLAL: Max * Max + Max", 3'd3,
                     32'hFFFFFFFF, 32'hFFFFFFFF, 32'hFFFFFFFF, 32'hFFFFFFFF,
                     32'hFFFFFFFF, 32'hFFFFFFFE);  // Overflow case
        
        // Summary
        repeat(10) @(posedge clk);
        $display("\n=== Test Summary ===");
        $display("Tests Run: %d", test_count);
        $display("Tests Passed: %d", test_passed);
        $display("Pass Rate: %.1f%%", (test_passed * 100.0) / test_count);
        
        if (test_passed == test_count) begin
            $display("\n✅ ALL MULTIPLY ACCUMULATION TESTS PASSED!");
        end else begin
            $display("\n❌ SOME MULTIPLY ACCUMULATION TESTS FAILED");
        end
        
        $finish;
    end
    
    // Timeout watchdog
    initial begin
        #10000; // 10us timeout
        $display("ERROR: Test timeout!");
        $finish;
    end
    
endmodule

sim/multiply_accum_test_tb.vcd
$date
	Fri Jul 25 11:26:35 2025
$end
$version
	Icarus Verilog
$end
$timescale
	1ps
$end
$scope module multiply_accum_test_tb $end
$var wire 1 ! zero $end
$var wire 1 " result_ready $end
$var wire 32 # result_lo [31:0] $end
$var wire 32 $ result_hi [31:0] $end
$var wire 1 % negative $end
$var reg 32 & acc_hi [31:0] $end
$var reg 32 ' acc_lo [31:0] $end
$var reg 1 ( clk $end
$var reg 1 ) mul_accumulate $end
$var reg 1 * mul_en $end
$var reg 1 + mul_long $end
$var reg 1 , mul_set_flags $end
$var reg 1 - mul_signed $end
$var reg 2 . mul_type [1:0] $end
$var reg 32 / operand_a [31:0] $end
$var reg 32 0 operand_b [31:0] $end
$var reg 1 1 rst_n $end
$var integer 32 2 test_count [31:0] $end
$var integer 32 3 test_passed [31:0] $end
$scope module u_multiply $end
$var wire 32 4 acc_hi [31:0] $end
$var wire 32 5 acc_lo [31:0] $end
$var wire 1 ( clk $end
$var wire 1 ) mul_accumulate $end
$var wire 1 * mul_en $end
$var wire 1 + mul_long $end
$var wire 1 , mul_set_flags $end
$var wire 1 - mul_signed $end
$var wire 2 6 mul_type [1:0] $end
$var wire 32 7 operand_a [31:0] $end
$var wire 32 8 operand_b [31:0] $end
$var wire 1 " result_ready $end
$var wire 1 1 rst_n $end
$var wire 1 ! zero $end
$var wire 32 9 result_lo [31:0] $end
$var wire 32 : result_hi [31:0] $end
$var wire 1 % negative $end
$var reg 64 ; accumulate_result [63:0] $end
$var reg 64 < accumulator [63:0] $end
$var reg 64 = final_result [63:0] $end
$var reg 32 > hi_sum [31:0] $end
$var reg 33 ? lo_sum [32:0] $end
$var reg 64 @ mul_result [63:0] $end
$upscope $end
$scope task test_multiply $end
$var reg 32 A a [31:0] $end
$var reg 32 B acc_h [31:0] $end
$var reg 32 C acc_l [31:0] $end
$var reg 32 D b [31:0] $end
$var reg 32 E exp_hi [31:0] $end
$var reg 32 F exp_lo [31:0] $end
$var reg 3 G test_type [2:0] $end
$upscope $end
$upscope $end
$enddefinitions $end
#0
$dumpvars
bx G
bx F
bx E
bx D
bx C
bx B
bx A
b0 @
b0 ?
b0 >
b0 =
b0 <
b0 ;
b0 :
b0 9
b0 8
b0 7
bx 6
b0 5
b0 4
b0 3
b0 2
01
b0 0
b0 /
bx .
x-
x,
x+
0*
x)
0(
b0 '
b0 &
0%
b0 $
b0 #
0"
x!
$end
#5000
1(
#10000
0(
#15000
1(
#20000
0(
#25000
1(
#30000
0(
#35000
1(
#40000
0(
#45000
11
1(
#50000
0(
#55000
1(
#60000
0(
#65000
1(
#70000
0(
#75000
1(
#80000
0(
#85000
1(
#90000
0(
#95000
b101101 #
b101101 9
0!
b101101 =
b101101 ;
b101101 ?
b1010 <
b100011 @
1"
1*
1,
1)
0-
0+
b1 .
b1 6
b1010 '
b1010 5
b111 0
b111 8
b101 /
b101 7
b1 2
b101101 F
b0 E
b1010 C
b0 B
b111 D
b101 A
b1 G
1(
#100000
0(
#105000
1(
#110000
0(
#115000
b1 3
0"
0*
1(
#120000
0(
#125000
b110000110101000 #
b110000110101000 9
b110000110101000 =
b110000110101000 ;
b110000110101000 ?
b1001110001000 <
b100111000100000 @
1"
1*
b1001110001000 '
b1001110001000 5
b11001000 0
b11001000 8
b1100100 /
b1100100 7
b10 2
b110000110101000 F
b1001110001000 C
b11001000 D
b1100100 A
1(
#130000
0(
#135000
1(
#140000
0(
#145000
b10 3
0"
0*
1(
#150000
0(
#155000
1%
b11111111111111110000000000000001 #
b11111111111111110000000000000001 9
b11111111111111110000000000000001 =
b11111111111111110000000000000001 ;
b11111111111111110000000000000001 ?
b10000000000000000 <
b11111111111111100000000000000001 @
1"
1*
b10000000000000000 '
b10000000000000000 5
b1111111111111111 0
b1111111111111111 8
b1111111111111111 /
b1111111111111111 7
b11 2
b11111111111111110000000000000001 F
b10000000000000000 C
b1111111111111111 D
b1111111111111111 A
1(
#160000
0(
#165000
1(
#170000
0(
#175000
b11 3
0"
0*
1(
#180000
0(
#185000
0%
b1 $
b1 :
b0 #
b0 9
b100000000000000000000000000000000 =
b100000000000000000000000000000000 ;
b1 >
b0 ?
b0 <
b100000000000000000000000000000000 @
1"
1*
1+
b11 .
b11 6
b0 '
b0 5
b10000000000000000 0
b10000000000000000 8
b10000000000000000 /
b10000000000000000 7
b100 2
b0 F
b1 E
b0 C
b10000000000000000 D
b10000000000000000 A
b11 G
1(
#190000
0(
#195000
1(
#200000
0(
#205000
b100 3
0"
0*
1(
#210000
0(
#215000
b10 $
b10 :
b11111111111111111111111111111111 #
b11111111111111111111111111111111 9
b1011111111111111111111111111111111 =
b1011111111111111111111111111111111 ;
b10 >
b11111111111111111111111111111111 ?
b100000000000000000000000000000001 <
b111111111111111111111111111111110 @
1"
1*
b1 '
b1 5
b1 &
b1 4
b10 0
b10 8
b11111111111111111111111111111111 /
b11111111111111111111111111111111 7
b101 2
b11111111111111111111111111111111 F
b10 E
b1 C
b1 B
b10 D
b11111111111111111111111111111111 A
1(
#220000
0(
#225000
1(
#230000
0(
#235000
b101 3
0"
0*
1(
#240000
0(
#245000
1%
b0 $
b0 :
b11111111111100001011110111000000 #
b11111111111100001011110111000000 9
b11111111111100001011110111000000 =
b1111111111111111111111111111111111111111111100001011110111000000 ;
b11111111111111111111111111111111 >
b11111111111100001011110111000000 ?
b0 <
b1111111111111111111111111111111111111111111100001011110111000000 @
1"
1*
1-
b1 .
b1 6
b0 '
b0 5
b0 &
b0 4
b1111101000 0
b1111101000 8
b11111111111111111111110000011000 /
b11111111111111111111110000011000 7
b110 2
b11111111111100001011110111000000 F
b11111111111111111111111111111111 E
b0 C
b0 B
b1111101000 D
b11111111111111111111110000011000 A
b101 G
1(
#250000
0(
#255000
1(
#260000
0(
#265000
0"
0*
1(
#270000
0(
#275000
0%
1!
b0 #
b0 9
b0 =
b0 ;
b0 >
b100000000000000000000000000000000 ?
b1111111111111111111111111111111111111111111111111111111111111111 <
b1 @
1"
1*
b11111111111111111111111111111111 '
b11111111111111111111111111111111 5
b11111111111111111111111111111111 &
b11111111111111111111111111111111 4
b11111111111111111111111111111111 0
b11111111111111111111111111111111 8
b11111111111111111111111111111111 /
b11111111111111111111111111111111 7
b111 2
b0 F
b0 E
b11111111111111111111111111111111 C
b11111111111111111111111111111111 B
b11111111111111111111111111111111 D
b11111111111111111111111111111111 A
1(
#280000
0(
#285000
1(
#290000
0(
#295000
b110 3
0"
0*
1(
#300000
0(
#305000
1%
0!
b11111111111111111111111111111110 #
b11111111111111111111111111111110 9
b11111111111111111111111111111110 =
b111111111111111111111111111111110 ;
b1 >
b11111111111111111111111111111110 ?
b100000000000000000000000000000000 <
b11111111111111111111111111111110 @
1"
1*
b0 '
b0 5
b1 &
b1 4
b10 0
b10 8
b1111111111111111111111111111111 /
b1111111111111111111111111111111 7
b1000 2
b11111111111111111111111111111110 F
b1 E
b0 C
b1 B
b10 D
b1111111111111111111111111111111 A
1(
#310000
0(
#315000
1(
#320000
0(
#325000
0"
0*
1(
#330000
0(
#335000
b11111111111111111111111111111111 #
b11111111111111111111111111111111 9
b11111111111111111111111111111111 =
b11111111111111111111111111111111 ;
b0 >
b11111111111111111111111111111111 ?
b11111111111111111111111111111111 <
b0 @
1"
1*
0-
0+
b11111111111111111111111111111111 '
b11111111111111111111111111111111 5
b0 &
b0 4
b0 0
b0 8
b0 /
b0 7
b1001 2
b11111111111111111111111111111111 F
b0 E
b11111111111111111111111111111111 C
b0 B
b0 D
b0 A
b1 G
1(
#340000
0(
#345000
1(
#350000
0(
#355000
b111 3
0"
0*
1(
#360000
0(
#365000
b11111111111111111111111111111110 $
b11111111111111111111111111111110 :
b0 #
b0 9
b1111111111111111111111111111111000000000000000000000000000000000 =
b1111111111111111111111111111111000000000000000000000000000000000 ;
b11111111111111111111111111111110 >
b100000000000000000000000000000000 ?
b1111111111111111111111111111111111111111111111111111111111111111 <
b1111111111111111111111111111111000000000000000000000000000000001 @
1"
1*
1+
b11 .
b11 6
b11111111111111111111111111111111 &
b11111111111111111111111111111111 4
b11111111111111111111111111111111 0
b11111111111111111111111111111111 8
b11111111111111111111111111111111 /
b11111111111111111111111111111111 7
b1010 2
b11111111111111111111111111111110 F
b11111111111111111111111111111111 E
b11111111111111111111111111111111 B
b11111111111111111111111111111111 D
b11111111111111111111111111111111 A
b11 G
1(
#370000
0(
#375000
1(
#380000
0(
#385000
0"
0*
1(
