rtl/arm7tdmi_decode.sv
import arm7tdmi_pkg::*;

module arm7tdmi_decode (
    input  logic        clk,
    input  logic        rst_n,
    
    // Input from fetch stage
    input  logic [31:0] instruction,
    input  logic [31:0] pc_in,
    input  logic        instr_valid,
    input  logic        thumb_mode,
    
    // Decoded instruction outputs
    output condition_t  condition,
    output instr_type_t instr_type,
    output alu_op_t     alu_op,
    output logic [3:0]  rd,      // Destination register
    output logic [3:0]  rn,      // First operand register
    output logic [3:0]  rm,      // Second operand register (if register)
    output logic [11:0] immediate, // Immediate value
    output logic        imm_en,   // Use immediate instead of register
    output logic        set_flags, // Update condition flags
    output shift_type_t shift_type,
    output logic [4:0]  shift_amount,
    
    // Branch instruction outputs
    output logic        is_branch,
    output logic [23:0] branch_offset,
    output logic        branch_link,
    
    // Memory instruction outputs
    output logic        is_memory,
    output logic        mem_load,   // 1 for load, 0 for store
    output logic        mem_byte,   // 1 for byte, 0 for word
    output logic        mem_pre,    // Pre-index
    output logic        mem_up,     // Add offset
    output logic        mem_writeback,
    
    // PSR transfer instruction outputs
    output logic        psr_to_reg,    // 1 for MRS, 0 for MSR
    output logic        psr_spsr,      // 1 for SPSR, 0 for CPSR
    output logic        psr_immediate, // 1 for immediate MSR
    
    // Coprocessor instruction outputs
    output cp_op_t      cp_op,         // Coprocessor operation type
    output logic [3:0]  cp_num,        // Coprocessor number (0-15)
    output logic [3:0]  cp_rd,         // Coprocessor destination register
    output logic [3:0]  cp_rn,         // Coprocessor operand register
    output logic [2:0]  cp_opcode1,    // Coprocessor opcode 1
    output logic [2:0]  cp_opcode2,    // Coprocessor opcode 2 (for CDP)
    output logic        cp_load,       // 1 for load, 0 for store (LDC/STC)
    
    // Output to execute stage
    output logic [31:0] pc_out,
    output logic        decode_valid,
    
    // Pipeline control
    input  logic        stall,
    input  logic        flush
);

    // Instruction fields (ARM format)
    logic [3:0]  cond_field;
    logic [1:0]  op_class;
    logic [5:0]  op_code;
    logic [3:0]  rd_field, rn_field, rm_field;
    logic [11:0] imm_field;
    logic        i_bit, s_bit;
    logic [1:0]  shift_type_field;
    logic [4:0]  shift_amt_field;
    
    // Branch instruction fields
    logic [23:0] branch_offset_field;
    logic        l_bit;
    
    // Memory instruction fields
    logic        p_bit, u_bit, b_bit, w_bit, l_bit_mem;
    
    // Decode registers
    logic [31:0] pc_reg;
    logic        valid_reg;
    
    // Extract instruction fields
    assign cond_field = instruction[31:28];
    assign op_class = instruction[27:26];
    assign i_bit = instruction[25];
    assign op_code = instruction[24:19];  // For data processing
    assign s_bit = instruction[20];
    assign rn_field = instruction[19:16];
    assign rd_field = instruction[15:12];
    assign rm_field = instruction[3:0];
    assign imm_field = instruction[11:0];
    assign shift_type_field = instruction[6:5];
    assign shift_amt_field = instruction[11:7];
    
    // Branch fields
    assign l_bit = instruction[24];
    assign branch_offset_field = instruction[23:0];
    
    // Memory fields
    assign p_bit = instruction[24];      // Pre/post index
    assign u_bit = instruction[23];      // Up/down
    assign b_bit = instruction[22];      // Byte/word
    assign w_bit = instruction[21];      // Write-back
    assign l_bit_mem = instruction[20];  // Load/store
    
    // Pipeline registers
    always_ff @(posedge clk or negedge rst_n) begin
        if (!rst_n) begin
            pc_reg <= 32'b0;
            valid_reg <= 1'b0;
        end else if (flush) begin
            pc_reg <= 32'b0;
            valid_reg <= 1'b0;
        end else if (!stall) begin
            pc_reg <= pc_in;
            valid_reg <= instr_valid;
        end
    end
    
    // Instruction type decode
    always_comb begin
        instr_type = INSTR_UNDEFINED;
        
        if (!thumb_mode) begin  // ARM mode
            casez (instruction[27:25])
                3'b000: begin
                    if (instruction[7:4] == 4'b1001) begin
                        if (instruction[24:21] == 4'b0000) begin
                            instr_type = INSTR_MUL;
                        end else begin
                            instr_type = INSTR_MUL_LONG;
                        end
                    end else if ((instruction[24:21] == 4'b1000 || instruction[24:21] == 4'b1010) && 
                                instruction[20] == 1'b0 && instruction[19:16] == 4'b1111 && instruction[11:0] == 12'b000000000000) begin
                        // MRS: Move PSR to register (check before SWP)
                        instr_type = INSTR_PSR_TRANSFER;
                    end else if ((instruction[24:21] == 4'b1001 || instruction[24:21] == 4'b1011) && 
                                instruction[11:4] == 8'b00000000) begin
                        // MSR: Move register to PSR
                        instr_type = INSTR_PSR_TRANSFER;
                    end else if (instruction[24:21] == 4'b1000 && instruction[7:4] == 4'b0000) begin
                        instr_type = INSTR_SINGLE_SWAP;
                    end else begin
                        instr_type = INSTR_DATA_PROC;
                    end
                end
                3'b001: begin
                    if (instruction[27:23] == 5'b00110 && instruction[21:20] == 2'b10) begin
                        // MSR: Move immediate to PSR
                        instr_type = INSTR_PSR_TRANSFER;
                    end else begin
                        instr_type = INSTR_DATA_PROC;
                    end
                end
                3'b010: instr_type = INSTR_SINGLE_DT;
                3'b011: instr_type = INSTR_SINGLE_DT;
                3'b100: instr_type = INSTR_BLOCK_DT;
                3'b101: instr_type = INSTR_BRANCH;
                3'b110: instr_type = INSTR_COPROCESSOR;
                3'b111: begin
                    if (instruction[24]) begin
                        instr_type = INSTR_SWI;
                    end else begin
                        instr_type = INSTR_COPROCESSOR;
                    end
                end
            endcase
        end else begin
            // TODO: Implement Thumb instruction decode
            instr_type = INSTR_UNDEFINED;
        end
    end
    
    // Condition decode
    assign condition = cond_field;
    
    // ALU operation decode (for data processing instructions)
    assign alu_op = instruction[24:21];
    
    // Register assignments
    assign rd = rd_field;
    assign rn = rn_field;
    assign rm = rm_field;
    assign immediate = imm_field;
    assign imm_en = i_bit && (instr_type == INSTR_DATA_PROC);
    assign set_flags = s_bit && (instr_type == INSTR_DATA_PROC);
    
    // Shift decode
    assign shift_type = shift_type_field;
    assign shift_amount = shift_amt_field;
    
    // Branch decode
    assign is_branch = (instr_type == INSTR_BRANCH);
    assign branch_offset = branch_offset_field;
    assign branch_link = l_bit && is_branch;
    
    // Memory decode
    assign is_memory = (instr_type == INSTR_SINGLE_DT) || (instr_type == INSTR_BLOCK_DT);
    assign mem_load = l_bit_mem;
    assign mem_byte = b_bit;
    assign mem_pre = p_bit;
    assign mem_up = u_bit;
    assign mem_writeback = w_bit;
    
    // PSR transfer decode
    assign psr_to_reg = (instr_type == INSTR_PSR_TRANSFER) && !instruction[21];  // MRS = L=0, MSR = L=1
    assign psr_spsr = (instr_type == INSTR_PSR_TRANSFER) && instruction[22];     // SPSR = R=1, CPSR = R=0  
    assign psr_immediate = (instr_type == INSTR_PSR_TRANSFER) && instruction[25]; // Immediate MSR
    
    // Coprocessor decode
    always_comb begin
        cp_op = CP_CDP;
        cp_num = 4'b0;
        cp_rd = 4'b0;
        cp_rn = 4'b0;
        cp_opcode1 = 3'b0;
        cp_opcode2 = 3'b0;
        cp_load = 1'b0;
        
        if (instr_type == INSTR_COPROCESSOR) begin
            cp_num = instruction[11:8];  // Coprocessor number
            
            if (instruction[27:25] == 3'b110) begin
                // LDC/STC - Coprocessor data transfer
                cp_rd = instruction[15:12];     // CRd
                cp_opcode1 = instruction[23:21]; // Opcode
                cp_load = instruction[20];       // L bit
                
                if (cp_load) begin
                    cp_op = CP_LDC;
                end else begin
                    cp_op = CP_STC;
                end
            end else if (instruction[27:25] == 3'b111) begin
                if (instruction[4]) begin
                    // MCR/MRC - Coprocessor register transfer
                    cp_rd = instruction[15:12];     // Rd (ARM register)
                    cp_rn = instruction[19:16];     // CRn (coprocessor register)
                    cp_opcode1 = instruction[23:21]; // Opcode 1
                    cp_opcode2 = instruction[7:5];   // Opcode 2
                    
                    if (instruction[20]) begin
                        cp_op = CP_MRC;  // Move to ARM from coprocessor
                    end else begin
                        cp_op = CP_MCR;  // Move to coprocessor from ARM
                    end
                end else begin
                    // CDP - Coprocessor data processing
                    cp_op = CP_CDP;
                    cp_rd = instruction[15:12];     // CRd
                    cp_rn = instruction[19:16];     // CRn
                    cp_opcode1 = instruction[23:21]; // Opcode 1
                    cp_opcode2 = instruction[7:5];   // Opcode 2
                end
            end
        end
    end
    
    // Outputs
    assign pc_out = pc_reg;
    assign decode_valid = valid_reg;
    
endmodule

sim/psr_decode_tb.sv
// PSR Transfer Decode Test
`timescale 1ns/1ps

import arm7tdmi_pkg::*;

module psr_decode_tb;
    
    // Clock and reset
    logic clk = 0;
    logic rst_n = 1;
    
    always #5 clk = ~clk;  // 100MHz clock
    
    // Decode module signals
    logic [31:0] instruction;
    logic [31:0] pc_in = 32'h0;
    logic        instr_valid = 1'b1;
    logic        thumb_mode = 1'b0;
    
    // Decode outputs
    condition_t     condition;
    instr_type_t    instr_type;
    alu_op_t        alu_op;
    logic [3:0]     rd, rn, rm;
    logic [11:0]    immediate;
    logic           imm_en, set_flags;
    shift_type_t    shift_type;
    logic [4:0]     shift_amount;
    logic           is_branch;
    logic [23:0]    branch_offset;
    logic           branch_link;
    logic           is_memory, mem_load, mem_byte;
    logic           mem_pre, mem_up, mem_writeback;
    logic           psr_to_reg, psr_spsr, psr_immediate;
    logic [31:0]    pc_out;
    logic           decode_valid;
    logic           stall = 1'b0, flush = 1'b0;
    
    // Instantiate decode module
    arm7tdmi_decode u_decode (
        .clk            (clk),
        .rst_n          (rst_n),
        .instruction    (instruction),
        .pc_in          (pc_in),
        .instr_valid    (instr_valid),
        .thumb_mode     (thumb_mode),
        .condition      (condition),
        .instr_type     (instr_type),
        .alu_op         (alu_op),
        .rd             (rd),
        .rn             (rn),
        .rm             (rm),
        .immediate      (immediate),
        .imm_en         (imm_en),
        .set_flags      (set_flags),
        .shift_type     (shift_type),
        .shift_amount   (shift_amount),
        .is_branch      (is_branch),
        .branch_offset  (branch_offset),
        .branch_link    (branch_link),
        .is_memory      (is_memory),
        .mem_load       (mem_load),
        .mem_byte       (mem_byte),
        .mem_pre        (mem_pre),
        .mem_up         (mem_up),
        .mem_writeback  (mem_writeback),
        .psr_to_reg     (psr_to_reg),
        .psr_spsr       (psr_spsr),
        .psr_immediate  (psr_immediate),
        .pc_out         (pc_out),
        .decode_valid   (decode_valid),
        .stall          (stall),
        .flush          (flush)
    );
    
    initial begin
        $dumpfile("psr_decode_tb.vcd");
        $dumpvars(0, psr_decode_tb);
        
        // Reset
        rst_n = 0;
        instruction = 32'h0;
        @(posedge clk);
        rst_n = 1;
        @(posedge clk);
        
        $display("=== PSR Transfer Decode Test ===");
        
        // Test 1: MRS R0, CPSR
        instruction = 32'hE10F0000;  // MRS R0, CPSR
        @(posedge clk);
        @(posedge clk);
        $display("Test 1 - MRS R0, CPSR (0x%08h):", instruction);
        $display("  instr_type = %d", instr_type);
        $display("  psr_to_reg = %b, psr_spsr = %b, psr_immediate = %b", psr_to_reg, psr_spsr, psr_immediate);
        $display("  rd = %d", rd);
        if (instr_type == INSTR_PSR_TRANSFER && psr_to_reg && !psr_spsr && !psr_immediate) begin
            $display("  PASS");
        end else begin
            $display("  FAIL");
        end
        
        // Test 2: MRS R1, SPSR  
        instruction = 32'hE14F1000;  // MRS R1, SPSR
        @(posedge clk);
        @(posedge clk);
        $display("Test 2 - MRS R1, SPSR (0x%08h):", instruction);
        $display("  instr_type = %d", instr_type);
        $display("  psr_to_reg = %b, psr_spsr = %b, psr_immediate = %b", psr_to_reg, psr_spsr, psr_immediate);
        $display("  rd = %d", rd);
        if (instr_type == INSTR_PSR_TRANSFER && psr_to_reg && psr_spsr && !psr_immediate) begin
            $display("  PASS");  
        end else begin
            $display("  FAIL");
        end
        
        // Test 3: MSR CPSR, R2
        instruction = 32'hE121F002;  // MSR CPSR, R2
        @(posedge clk);
        @(posedge clk);
        $display("Test 3 - MSR CPSR, R2 (0x%08h):", instruction);
        $display("  instr_type = %d", instr_type);
        $display("  psr_to_reg = %b, psr_spsr = %b, psr_immediate = %b", psr_to_reg, psr_spsr, psr_immediate);
        $display("  rm = %d", rm);
        if (instr_type == INSTR_PSR_TRANSFER && !psr_to_reg && !psr_spsr && !psr_immediate) begin
            $display("  PASS");
        end else begin
            $display("  FAIL");
        end
        
        // Test 4: MSR SPSR, R3
        instruction = 32'hE161F003;  // MSR SPSR, R3  
        @(posedge clk);
        @(posedge clk);
        $display("Test 4 - MSR SPSR, R3 (0x%08h):", instruction);
        $display("  instr_type = %d", instr_type);
        $display("  psr_to_reg = %b, psr_spsr = %b, psr_immediate = %b", psr_to_reg, psr_spsr, psr_immediate);
        $display("  rm = %d", rm);
        if (instr_type == INSTR_PSR_TRANSFER && !psr_to_reg && psr_spsr && !psr_immediate) begin
            $display("  PASS");
        end else begin
            $display("  FAIL");
        end
        
        // Test 5: MSR CPSR_flg, #0xF0000000  
        instruction = 32'hE32FF00F;  // MSR CPSR_flg, #0xF0000000
        @(posedge clk);
        @(posedge clk);
        $display("Test 5 - MSR CPSR_flg, #0xF0000000 (0x%08h):", instruction);
        $display("  instr_type = %d", instr_type);
        $display("  psr_to_reg = %b, psr_spsr = %b, psr_immediate = %b", psr_to_reg, psr_spsr, psr_immediate);
        $display("  immediate = 0x%03h", immediate);
        if (instr_type == INSTR_PSR_TRANSFER && !psr_to_reg && !psr_spsr && psr_immediate) begin
            $display("  PASS");
        end else begin
            $display("  FAIL");
        end
        
        // Test 6: Regular data processing instruction (should not be PSR transfer)
        instruction = 32'hE0800001;  // ADD R0, R0, R1
        @(posedge clk);
        @(posedge clk);
        $display("Test 6 - ADD R0, R0, R1 (0x%08h):", instruction);
        $display("  instr_type = %d", instr_type);
        if (instr_type == INSTR_DATA_PROC) begin
            $display("  PASS - Correctly identified as data processing");
        end else begin
            $display("  FAIL - Should be data processing, got %d", instr_type);
        end
        
        $display("=== PSR Decode Test Complete ===");
        $finish;
    end
    
endmodule

sim/psr_decode_tb.vcd
$date
	Thu Jul 24 14:15:42 2025
$end
$version
	Icarus Verilog
$end
$timescale
	1ps
$end
$scope module psr_decode_tb $end
$var wire 2 ! shift_type [1:0] $end
$var wire 5 " shift_amount [4:0] $end
$var wire 1 # set_flags $end
$var wire 4 $ rn [3:0] $end
$var wire 4 % rm [3:0] $end
$var wire 4 & rd [3:0] $end
$var wire 1 ' psr_to_reg $end
$var wire 1 ( psr_spsr $end
$var wire 1 ) psr_immediate $end
$var wire 32 * pc_out [31:0] $end
$var wire 1 + mem_writeback $end
$var wire 1 , mem_up $end
$var wire 1 - mem_pre $end
$var wire 1 . mem_load $end
$var wire 1 / mem_byte $end
$var wire 1 0 is_memory $end
$var wire 1 1 is_branch $end
$var wire 4 2 instr_type [3:0] $end
$var wire 12 3 immediate [11:0] $end
$var wire 1 4 imm_en $end
$var wire 1 5 decode_valid $end
$var wire 4 6 condition [3:0] $end
$var wire 24 7 branch_offset [23:0] $end
$var wire 1 8 branch_link $end
$var wire 4 9 alu_op [3:0] $end
$var reg 1 : clk $end
$var reg 1 ; flush $end
$var reg 1 < instr_valid $end
$var reg 32 = instruction [31:0] $end
$var reg 32 > pc_in [31:0] $end
$var reg 1 ? rst_n $end
$var reg 1 @ stall $end
$var reg 1 A thumb_mode $end
$scope module u_decode $end
$var wire 1 8 branch_link $end
$var wire 24 B branch_offset [23:0] $end
$var wire 1 : clk $end
$var wire 4 C condition [3:0] $end
$var wire 1 5 decode_valid $end
$var wire 1 ; flush $end
$var wire 1 4 imm_en $end
$var wire 12 D immediate [11:0] $end
$var wire 1 < instr_valid $end
$var wire 32 E instruction [31:0] $end
$var wire 1 0 is_memory $end
$var wire 1 / mem_byte $end
$var wire 1 . mem_load $end
$var wire 1 - mem_pre $end
$var wire 1 , mem_up $end
$var wire 1 + mem_writeback $end
$var wire 32 F pc_in [31:0] $end
$var wire 32 G pc_out [31:0] $end
$var wire 1 ) psr_immediate $end
$var wire 1 ( psr_spsr $end
$var wire 1 ' psr_to_reg $end
$var wire 4 H rd [3:0] $end
$var wire 4 I rm [3:0] $end
$var wire 4 J rn [3:0] $end
$var wire 1 ? rst_n $end
$var wire 1 # set_flags $end
$var wire 5 K shift_amount [4:0] $end
$var wire 2 L shift_type [1:0] $end
$var wire 1 @ stall $end
$var wire 1 A thumb_mode $end
$var wire 1 M w_bit $end
$var wire 1 N u_bit $end
$var wire 2 O shift_type_field [1:0] $end
$var wire 5 P shift_amt_field [4:0] $end
$var wire 1 Q s_bit $end
$var wire 4 R rn_field [3:0] $end
$var wire 4 S rm_field [3:0] $end
$var wire 4 T rd_field [3:0] $end
$var wire 1 U p_bit $end
$var wire 6 V op_code [5:0] $end
$var wire 2 W op_class [1:0] $end
$var wire 1 X l_bit_mem $end
$var wire 1 Y l_bit $end
$var wire 1 1 is_branch $end
$var wire 12 Z imm_field [11:0] $end
$var wire 1 [ i_bit $end
$var wire 4 \ cond_field [3:0] $end
$var wire 24 ] branch_offset_field [23:0] $end
$var wire 1 ^ b_bit $end
$var wire 4 _ alu_op [3:0] $end
$var reg 1 ` cp_load $end
$var reg 4 a cp_num [3:0] $end
$var reg 3 b cp_op [2:0] $end
$var reg 3 c cp_opcode1 [2:0] $end
$var reg 3 d cp_opcode2 [2:0] $end
$var reg 4 e cp_rd [3:0] $end
$var reg 4 f cp_rn [3:0] $end
$var reg 4 g instr_type [3:0] $end
$var reg 32 h pc_reg [31:0] $end
$var reg 1 i valid_reg $end
$upscope $end
$upscope $end
$enddefinitions $end
#0
$dumpvars
0i
b0 h
b0 g
b0 f
b0 e
b0 d
b0 c
b0 b
b0 a
0`
b0 _
0^
b0 ]
b0 \
0[
b0 Z
0Y
0X
b0 W
b0 V
0U
b0 T
b0 S
b0 R
0Q
b0 P
b0 O
0N
0M
b0 L
b0 K
b0 J
b0 I
b0 H
b0 G
b0 F
b0 E
b0 D
b0 C
b0 B
0A
0@
0?
b0 >
b0 =
1<
0;
0:
b0 9
08
b0 7
b0 6
05
04
b0 3
b0 2
01
00
0/
0.
0-
0,
0+
b0 *
0)
0(
0'
b0 &
b0 %
b0 $
0#
b0 "
b0 !
$end
#5000
15
1i
1?
1:
#10000
0:
#15000
1'
b1100 2
b1100 g
b1110 6
b1110 C
b1110 \
b100001 V
b1111 $
b1111 J
b1111 R
1Y
b11110000000000000000 7
b11110000000000000000 B
b11110000000000000000 ]
1-
1U
b1000 9
b1000 _
b11100001000011110000000000000000 =
b11100001000011110000000000000000 E
1:
#20000
0:
#25000
1:
#30000
0:
#35000
1(
b1100 2
b1100 g
b101001 V
b1 &
b1 H
b1 T
b10011110001000000000000 7
b10011110001000000000000 B
b10011110001000000000000 ]
1/
1^
b1010 9
b1010 _
b11100001010011110001000000000000 =
b11100001010011110001000000000000 E
1:
#40000
0:
#45000
1:
#50000
0:
#55000
0'
0(
b1100 2
b1100 g
b100100 V
b1 $
b1 J
b1 R
b1111 &
b1111 H
b1111 T
b10 %
b10 I
b10 S
b10 3
b10 D
b10 Z
b1000011111000000000010 7
b1000011111000000000010 B
b1000011111000000000010 ]
0/
0^
1+
1M
b1001 9
b1001 _
b11100001001000011111000000000010 =
b11100001001000011111000000000010 E
1:
#60000
0:
#65000
1:
#70000
0:
#75000
1(
b1100 2
b1100 g
b101100 V
b11 %
b11 I
b11 S
b11 3
b11 D
b11 Z
b11000011111000000000011 7
b11000011111000000000011 B
b11000011111000000000011 ]
1/
1^
b1011 9
b1011 _
b11100001011000011111000000000011 =
b11100001011000011111000000000011 E
1:
#80000
0:
#85000
1:
#90000
0:
#95000
0(
1)
b1100 2
b1100 g
1[
b100101 V
b1111 $
b1111 J
b1111 R
b1111 %
b1111 I
b1111 S
b1111 3
b1111 D
b1111 Z
b1011111111000000001111 7
b1011111111000000001111 B
b1011111111000000001111 ]
0/
0^
b1001 9
b1001 _
b11100011001011111111000000001111 =
b11100011001011111111000000001111 E
1:
#100000
0:
#105000
1:
#110000
0:
#115000
0)
b0 2
b0 g
0[
b10000 V
b0 $
b0 J
b0 R
b0 &
b0 H
b0 T
b1 %
b1 I
b1 S
b1 3
b1 D
b1 Z
0Y
b100000000000000000000001 7
b100000000000000000000001 B
b100000000000000000000001 ]
0-
0U
1,
1N
0+
0M
b100 9
b100 _
b11100000100000000000000000000001 =
b11100000100000000000000000000001 E
1:
